Workbook

Sheet int_ai_sample
A1: review_id | B1: order_id | C1: review_score | D1: review_comment_title_message | E1: review_translation_tw | F1: sentiment | G1: t01_delivery_logistics | H1: t02_order_fulfillment | I1: t03_product_quality | J1: t04_product_consistency | K1: t05_packaging_protection | L1: t06_customer_service | M1: t07_price_transaction | N1: t08_platform_system
A2: 03bd089dca1ac0d71c2868eb3483618a | B2: 03fab3cde6e6bb6b6715075147044dca | C2: 4 | D2: Boa noite,, compro nas lojas lannister a 8 anos e recomendo, pois tudo chega dentro do prazo, e com a mesma qualidade que é apresentado no site, muito obrigado por fazer parte da minha família. | E2: 晚上好，我在 lannister 的實體店買了8年，還是會推薦，因為所有商品都會在期限內送到，而且品質跟網站上展示的一樣。非常感謝，能成為你們的一家人。 | F2: positive | G2: 1 | H2: 0 | I2: 1 | J2: 1 | K2: 0 | L2: 0 | M2: 0 | N2: 0
A3: 056ff087f8e5fe614bc6cce3caa0c480 | B3: fd9ec02005605e0b338a29e03bc6eb30 | C3: 5 | D3: O produto chegou muito antes do prazo e veio em ótimas condições! | E3: 商品比預期更早送到，而且狀態非常好！ | F3: positive | G3: 1 | H3: 0 | I3: 0 | J3: 0 | K3: 0 | L3: 0 | M3: 0 | N3: 0
A4: 0721c1573e47ecabab85980373191514 | B4: 2a661a72ecdfcc8872e968ce3856d59e | C4: 5 | D4: Ótimo produto | E4: 很棒的商品。 | F4: positive | G4: 0 | H4: 0 | I4: 0 | J4: 0 | K4: 0 | L4: 0 | M4: 0 | N4: 0
A5: 074c39cb5e90578eaeb560e6f632ae1e | B5: 2edf506c823b1a3bc6d134864bc4c10c | C5: 1 | D5: Produto de péssima qualidade e acabamento. | E5: 商品品質很差，做工和表面處理也很粗糙。 | F5: negative | G5: 0 | H5: 0 | I5: 1 | J5: 0 | K5: 0 | L5: 0 | M5: 0 | N5: 0
A6: 0c0cb90ec2c6217be6fcfd688817e683 | B6: 6b1a5aabdde7ed25268697cef2a9d28a | C6: 3 | D6: RECEBI NO PRAZO ESTIPULADO. | E6: 在指定期限內收到。 | F6: positive | G6: 1 | H6: 0 | I6: 0 | J6: 0 | K6: 0 | L6: 0 | M6: 0 | N6: 0
A7: 0c945ea8559964747662519dbddda79b | B7: bc107b9b5508d2356f663898c2eb1d8b | C7: 1 | D7: NÃO recebi o produto. | E7: 我沒有收到商品。 | F7: negative | G7: 1 | H7: 0 | I7: 0 | J7: 0 | K7: 0 | L7: 0 | M7: 0 | N7: 0
A8: 0d85b938527456657c1435b3e0cf7726 | B8: 58ddcc041323f47709f7e0b0a461c466 | C8: 4 | D8: Otimo Prazo da entrega bem rápido | E8: 很棒，交貨時間很快。 | F8: positive | G8: 1 | H8: 0 | I8: 0 | J8: 0 | K8: 0 | L8: 0 | M8: 0 | N8: 0
A9: 0f508c7aba0bbe43ee80975436fd3d5d | B9: 51c7735438088dc983751f683f652995 | C9: 4 | D9: O produto foi entregue correta e rapidamente. Já foi testado e aprovado. Sugiro reforçarem a estrutura plástica, principalmente da torre da manivela, para dar maior firmeza ao movimento. Obrigada. | E9: 商品送達正確而且很快。已經測試過並通過驗收。建議加強塑膠結構，特別是曲柄塔，讓動作更穩固。謝謝。 | F9: positive | G9: 1 | H9: 0 | I9: 1 | J9: 0 | K9: 0 | L9: 0 | M9: 0 | N9: 0
A10: 10460eaad2a97e45e5735e7058d778b3 | B10: fec2c513cc9c10087af9e5d8f2da71fd | C10: 3 | D10: produto com aparência de usado, tinta da logo gasta e com alguns arranhões, não tente economizar 5 reais comprando por essa loja. | E10: 商品看起來像二手，logo 的漆都磨掉了，還有一些刮痕。不要想省 5 塊錢而買這家店的東西。 | F10: negative | G10: 0 | H10: 0 | I10: 1 | J10: 0 | K10: 0 | L10: 0 | M10: 0 | N10: 0
A11: 1110fd4c2db3d0f9df542b46aebcbfbd | B11: dc9c5e38f7f39900731ed6c79a2c4849 | C11: 5 | D11: Boa tarde... Recebi sim meu produto, mas a lancheira deu problema na alça ela descosturou, como faço para trocar... | E11: 下午好……我有收到商品，但保溫便當包的提把出問題了，線縫脫開了。我該怎麼換？ | F11: negative | G11: 0 | H11: 0 | I11: 1 | J11: 0 | K11: 0 | L11: 1 | M11: 0 | N11: 0
A12: 14bd0f4bea843699f4da3b65e10cccae | B12: bca23b0c0c24178fcf6fb1838fadbe86 | C12: 4 | D12: Entregue antes do prazo, frete mais caro que o da lannister. Parece muito bom, as primeiras pedaladas deram impressão muito boa. Não veio manual de instrução, porém a montagem foi fácil e intuitiv | E12: 比預期更早到貨，運費比 lannister 的更貴。看起來非常不錯，前幾次踩踏的感覺很好。但沒有附說明手冊，不過組裝很容易也很直覺。 | F12: mixed | G12: 1 | H12: 0 | I12: 1 | J12: 0 | K12: 0 | L12: 0 | M12: 1 | N12: 0
A13: 1e8f7bf12393c8879303b37abf5e58fb | B13: 6105321bd9c6d494502e32dd1d28c53d | C13: 1 | D13: pedi um produto e no lugar veio outro responsavel ficou de enviar p correto, estou aguardando | E13: 我訂的是一個商品，但送來的卻是另一個。對方說會再寄正確的，但我現在還在等。 | F13: negative | G13: 0 | H13: 1 | I13: 0 | J13: 0 | K13: 0 | L13: 1 | M13: 0 | N13: 0
... A101: ff77e689593e261a118f2227b72976f3 | B101: 8d1bc6d158769393c1ec54c05b734652 | C101: 2 | D101: Já sou cliente a um bom tempo e entendo o atraso mais esse deveria ser o diferencial os produtos já sabemos da qualidade exelente... | E101: 我已經是客戶一段時間了，也理解延遲，但這次應該是賣家的差異點；產品品質我們都知道很優。 | F101: mixed | G101: 1 | H101: 0 | I101: 0 | J101: 0 | K101: 0 | L101: 0 | M101: 0 | N101: 0

Sheet 人工標註
A1: review_id | B1: order_id | C1: review_score | D1: review_comment_title_message | E1: review_translation_tw | F1: sentiment人工標注 | G1: t01_delivery_logistics | H1: t02_order_fulfillment | I1: t03_product_quality | J1: t04_product_consistency | K1: t05_packaging_protection | L1: t06_customer_service | M1: t07_price_transaction | N1: t08_platform_system
A2: 03bd089dca1ac0d71c2868eb3483618a | B2: 03fab3cde6e6bb6b6715075147044dca | C2: 4 | D2: Boa noite,, compro nas lojas lannister a 8 anos e recomendo, pois tudo chega dentro do prazo, e com a mesma qualidade que é apresentado no site, muito obrigado por fazer parte da minha família. | E2: 晚上好，我在 lannister 的實體店買了8年，還是會推薦，因為所有商品都會在期限內送到，而且品質跟網站上展示的一樣。非常感謝，能成為你們的一家人。 | F2: positive | G2: 1 | H2: 0 | I2: 0 | J2: 1 | K2: 0 | L2: 0 | M2: 0 | N2: 0
A3: 056ff087f8e5fe614bc6cce3caa0c480 | B3: fd9ec02005605e0b338a29e03bc6eb30 | C3: 5 | D3: O produto chegou muito antes do prazo e veio em ótimas condições! | E3: 商品比預期更早送到，而且狀態非常好！ | F3: positive | G3: 1 | H3: 0 | I3: 0 | J3: 1 | K3: 0 | L3: 0 | M3: 0 | N3: 0
A4: 0721c1573e47ecabab85980373191514 | B4: 2a661a72ecdfcc8872e968ce3856d59e | C4: 5 | D4: Ótimo produto | E4: 很棒的商品。 | F4: positive | G4: 0 | H4: 0 | I4: 1 | J4: 0 | K4: 0 | L4: 0 | M4: 0 | N4: 0
A5: 074c39cb5e90578eaeb560e6f632ae1e | B5: 2edf506c823b1a3bc6d134864bc4c10c | C5: 1 | D5: Produto de péssima qualidade e acabamento. | E5: 商品品質很差，做工和表面處理也很粗糙。 | F5: negative | G5: 0 | H5: 0 | I5: 1 | J5: 0 | K5: 0 | L5: 0 | M5: 0 | N5: 0
A6: 0c0cb90ec2c6217be6fcfd688817e683 | B6: 6b1a5aabdde7ed25268697cef2a9d28a | C6: 3 | D6: RECEBI NO PRAZO ESTIPULADO. | E6: 在指定期限內收到。 | F6: positive | G6: 1 | H6: 0 | I6: 0 | J6: 0 | K6: 0 | L6: 0 | M6: 0 | N6: 0
A7: 0c945ea8559964747662519dbddda79b | B7: bc107b9b5508d2356f663898c2eb1d8b | C7: 1 | D7: NÃO recebi o produto. | E7: 我沒有收到商品。 | F7: negative | G7: 1 | H7: 0 | I7: 0 | J7: 0 | K7: 0 | L7: 0 | M7: 0 | N7: 0
A8: 0d85b938527456657c1435b3e0cf7726 | B8: 58ddcc041323f47709f7e0b0a461c466 | C8: 4 | D8: Otimo Prazo da entrega bem rápido | E8: 很棒，交貨時間很快。 | F8: positive | G8: 1 | H8: 0 | I8: 0 | J8: 0 | K8: 0 | L8: 0 | M8: 0 | N8: 0
A9: 0f508c7aba0bbe43ee80975436fd3d5d | B9: 51c7735438088dc983751f683f652995 | C9: 4 | D9: O produto foi entregue correta e rapidamente. Já foi testado e aprovado. Sugiro reforçarem a estrutura plástica, principalmente da torre da manivela, para dar maior firmeza ao movimento. Obrigada. | E9: 商品送達正確而且很快。已經測試過並通過驗收。建議加強塑膠結構，特別是曲柄塔，讓動作更穩固。謝謝。 | F9: mixed | G9: 1 | H9: 0 | I9: 1 | J9: 0 | K9: 0 | L9: 0 | M9: 0 | N9: 0
A10: 10460eaad2a97e45e5735e7058d778b3 | B10: fec2c513cc9c10087af9e5d8f2da71fd | C10: 3 | D10: produto com aparência de usado, tinta da logo gasta e com alguns arranhões, não tente economizar 5 reais comprando por essa loja. | E10: 商品看起來像二手，logo 的漆都磨掉了，還有一些刮痕。不要想省 5 塊錢而買這家店的東西。 | F10: negative | G10: 0 | H10: 0 | I10: 1 | J10: 0 | K10: 0 | L10: 0 | M10: 0 | N10: 0
A11: 1110fd4c2db3d0f9df542b46aebcbfbd | B11: dc9c5e38f7f39900731ed6c79a2c4849 | C11: 5 | D11: Boa tarde... Recebi sim meu produto, mas a lancheira deu problema na alça ela descosturou, como faço para trocar... | E11: 下午好……我有收到商品，但保溫便當包的提把出問題了，線縫脫開了。我該怎麼換？ | F11: negative | G11: 0 | H11: 0 | I11: 1 | J11: 0 | K11: 0 | L11: 0 | M11: 0 | N11: 0
A12: 14bd0f4bea843699f4da3b65e10cccae | B12: bca23b0c0c24178fcf6fb1838fadbe86 | C12: 4 | D12: Entregue antes do prazo, frete mais caro que o da lannister. Parece muito bom, as primeiras pedaladas deram impressão muito boa. Não veio manual de instrução, porém a montagem foi fácil e intuitiv | E12: 比預期更早到貨，運費比 lannister 的更貴。看起來非常不錯，前幾次踩踏的感覺很好。但沒有附說明手冊，不過組裝很容易也很直覺。 | F12: mixed | G12: 1 | H12: 0 | I12: 0 | J12: 0 | K12: 0 | L12: 0 | M12: 1 | N12: 0
A13: 1e8f7bf12393c8879303b37abf5e58fb | B13: 6105321bd9c6d494502e32dd1d28c53d | C13: 1 | D13: pedi um produto e no lugar veio outro responsavel ficou de enviar p correto, estou aguardando | E13: 我訂的是一個商品，但送來的卻是另一個。對方說會再寄正確的，但我現在還在等。 | F13: negative | G13: 0 | H13: 1 | I13: 0 | J13: 0 | K13: 0 | L13: 0 | M13: 0 | N13: 0
... A30: 467429497f2711eb1e33e710897e04a8 | B30: 91811480f57d846cb6b5b418b549f158 | C30: 4 | D30: Bom produto gostei E parabéns a loja q entregou antes do prazo Recomendo | E30: 不錯的產品，我喜歡！也恭喜你們店家，提前交貨！我推薦。 | F30: positive | G30: 1 | H30: 0 | I30: 0 | J30: 0 | K30: 0 | L30: 0 | M30: 0 | N30: 0

Sheet 人工標註正確率
A1: review_id | B1: review_score | C1: review_translation_tw | D1: sentiment_AI | E1: sentiment_人工 | F1: Sentiment是否正確 | G1: Sentiment Accuracy | H1: T01是否正確 | I1: T02是否正確 | J1: T03是否正確 | K1: T04是否正確 | L1: T05是否正確 | M1: T06是否正確 | N1: T07是否正確 | O1: T08是否正確 | Q1: AI 標注驗證 KPI
A2: 03bd089dca1ac0d71c2868eb3483618a | B2: =IFERROR(VLOOKUP($A2,int_ai_sample!$A$2:$N$101,3,FALSE),"") -> 4 | C2: =IFERROR(VLOOKUP($A2,int_ai_sample!$A$2:$N$101,5,FALSE),"") -> 晚上好，我在 lannister 的實體店買了8年，還是會推薦，因為所有商品都會在期限內送到，而且品質跟網站上展示的一樣。非常感謝，能成為你們的一家人。 | D2: =IFERROR(VLOOKUP($A2,int_ai_sample!$A$2:$N$101,6,FALSE),"") -> positive | E2: =IFERROR(VLOOKUP($A2,人工標註!$A$2:$N$30,6,FALSE),"") -> positive | F2: =IF(OR(D2="",E2=""),"",IF(D2=E2,"是","否")) -> 是 | G2: =IFERROR(COUNTIF($F$2:$F$30,"是")/COUNTA($A$2:$A$30),0) -> 0.86206897 | H2: =IFERROR(IF(VLOOKUP($A2,int_ai_sample!$A$2:$N$101,7,FALSE)=VLOOKUP($A2,人工標註!$A$2:$N$30,7,FALSE),"是","否"),"") -> 是 | I2: =IFERROR(IF(VLOOKUP($A2,int_ai_sample!$A$2:$N$101,8,FALSE)=VLOOKUP($A2,人工標註!$A$2:$N$30,8,FALSE),"是","否"),"") -> 是 | J2: =IFERROR(IF(VLOOKUP($A2,int_ai_sample!$A$2:$N$101,9,FALSE)=VLOOKUP($A2,人工標註!$A$2:$N$30,9,FALSE),"是","否"),"") -> 否 | K2: =IFERROR(IF(VLOOKUP($A2,int_ai_sample!$A$2:$N$101,10,FALSE)=VLOOKUP($A2,人工標註!$A$2:$N$30,10,FALSE),"是","否"),"") -> 是 | L2: =IFERROR(IF(VLOOKUP($A2,int_ai_sample!$A$2:$N$101,11,FALSE)=VLOOKUP($A2,人工標註!$A$2:$N$30,11,FALSE),"是","否"),"") -> 是 | M2: =IFERROR(IF(VLOOKUP($A2,int_ai_sample!$A$2:$N$101,12,FALSE)=VLOOKUP($A2,人工標註!$A$2:$N$30,12,FALSE),"是","否"),"") -> 是 | N2: =IFERROR(IF(VLOOKUP($A2,int_ai_sample!$A$2:$N$101,13,FALSE)=VLOOKUP($A2,人工標註!$A$2:$N$30,13,FALSE),"是","否"),"") -> 是 | O2: =IFERROR(IF(VLOOKUP($A2,int_ai_sample!$A$2:$N$101,14,FALSE)=VLOOKUP($A2,人工標註!$A$2:$N$30,14,FALSE),"是","否"),"") -> 是 | Q2: 有效樣本數 | R2: =COUNTA($A$2:$A$30) -> 29
A3: 056ff087f8e5fe614bc6cce3caa0c480 | B3: =IFERROR(VLOOKUP($A3,int_ai_sample!$A$2:$N$101,3,FALSE),"") -> 5 | C3: =IFERROR(VLOOKUP($A3,int_ai_sample!$A$2:$N$101,5,FALSE),"") -> 商品比預期更早送到，而且狀態非常好！ | D3: =IFERROR(VLOOKUP($A3,int_ai_sample!$A$2:$N$101,6,FALSE),"") -> positive | E3: =IFERROR(VLOOKUP($A3,人工標註!$A$2:$N$30,6,FALSE),"") -> positive | F3: =IF(OR(D3="",E3=""),"",IF(D3=E3,"是","否")) -> 是 | G3: =ROUND(COUNTIF($F$2:$F$30,"是")/30,2) -> 0.83 | H3: =IFERROR(IF(VLOOKUP($A3,int_ai_sample!$A$2:$N$101,7,FALSE)=VLOOKUP($A3,人工標註!$A$2:$N$30,7,FALSE),"是","否"),"") -> 是 | I3: =IFERROR(IF(VLOOKUP($A3,int_ai_sample!$A$2:$N$101,8,FALSE)=VLOOKUP($A3,人工標註!$A$2:$N$30,8,FALSE),"是","否"),"") -> 是 | J3: =IFERROR(IF(VLOOKUP($A3,int_ai_sample!$A$2:$N$101,9,FALSE)=VLOOKUP($A3,人工標註!$A$2:$N$30,9,FALSE),"是","否"),"") -> 是 | K3: =IFERROR(IF(VLOOKUP($A3,int_ai_sample!$A$2:$N$101,10,FALSE)=VLOOKUP($A3,人工標註!$A$2:$N$30,10,FALSE),"是","否"),"") -> 否 | L3: =IFERROR(IF(VLOOKUP($A3,int_ai_sample!$A$2:$N$101,11,FALSE)=VLOOKUP($A3,人工標註!$A$2:$N$30,11,FALSE),"是","否"),"") -> 是 | M3: =IFERROR(IF(VLOOKUP($A3,int_ai_sample!$A$2:$N$101,12,FALSE)=VLOOKUP($A3,人工標註!$A$2:$N$30,12,FALSE),"是","否"),"") -> 是 | N3: =IFERROR(IF(VLOOKUP($A3,int_ai_sample!$A$2:$N$101,13,FALSE)=VLOOKUP($A3,人工標註!$A$2:$N$30,13,FALSE),"是","否"),"") -> 是 | O3: =IFERROR(IF(VLOOKUP($A3,int_ai_sample!$A$2:$N$101,14,FALSE)=VLOOKUP($A3,人工標註!$A$2:$N$30,14,FALSE),"是","否"),"") -> 是 | Q3: Sentiment Accuracy | R3: =IFERROR(COUNTIF($F$2:$F$30,"是")/R2,0) -> 0.86206897
A4: 0721c1573e47ecabab85980373191514 | B4: =IFERROR(VLOOKUP($A4,int_ai_sample!$A$2:$N$101,3,FALSE),"") -> 5 | C4: =IFERROR(VLOOKUP($A4,int_ai_sample!$A$2:$N$101,5,FALSE),"") -> 很棒的商品。 | D4: =IFERROR(VLOOKUP($A4,int_ai_sample!$A$2:$N$101,6,FALSE),"") -> positive | E4: =IFERROR(VLOOKUP($A4,人工標註!$A$2:$N$30,6,FALSE),"") -> positive | F4: =IF(OR(D4="",E4=""),"",IF(D4=E4,"是","否")) -> 是 | G4: =ROUND(COUNTIF($F$2:$F$30,"是")/30,2) -> 0.83 | H4: =IFERROR(IF(VLOOKUP($A4,int_ai_sample!$A$2:$N$101,7,FALSE)=VLOOKUP($A4,人工標註!$A$2:$N$30,7,FALSE),"是","否"),"") -> 是 | I4: =IFERROR(IF(VLOOKUP($A4,int_ai_sample!$A$2:$N$101,8,FALSE)=VLOOKUP($A4,人工標註!$A$2:$N$30,8,FALSE),"是","否"),"") -> 是 | J4: =IFERROR(IF(VLOOKUP($A4,int_ai_sample!$A$2:$N$101,9,FALSE)=VLOOKUP($A4,人工標註!$A$2:$N$30,9,FALSE),"是","否"),"") -> 否 | K4: =IFERROR(IF(VLOOKUP($A4,int_ai_sample!$A$2:$N$101,10,FALSE)=VLOOKUP($A4,人工標註!$A$2:$N$30,10,FALSE),"是","否"),"") -> 是 | L4: =IFERROR(IF(VLOOKUP($A4,int_ai_sample!$A$2:$N$101,11,FALSE)=VLOOKUP($A4,人工標註!$A$2:$N$30,11,FALSE),"是","否"),"") -> 是 | M4: =IFERROR(IF(VLOOKUP($A4,int_ai_sample!$A$2:$N$101,12,FALSE)=VLOOKUP($A4,人工標註!$A$2:$N$30,12,FALSE),"是","否"),"") -> 是 | N4: =IFERROR(IF(VLOOKUP($A4,int_ai_sample!$A$2:$N$101,13,FALSE)=VLOOKUP($A4,人工標註!$A$2:$N$30,13,FALSE),"是","否"),"") -> 是 | O4: =IFERROR(IF(VLOOKUP($A4,int_ai_sample!$A$2:$N$101,14,FALSE)=VLOOKUP($A4,人工標註!$A$2:$N$30,14,FALSE),"是","否"),"") -> 是
A5: 074c39cb5e90578eaeb560e6f632ae1e | B5: =IFERROR(VLOOKUP($A5,int_ai_sample!$A$2:$N$101,3,FALSE),"") -> 1 | C5: =IFERROR(VLOOKUP($A5,int_ai_sample!$A$2:$N$101,5,FALSE),"") -> 商品品質很差，做工和表面處理也很粗糙。 | D5: =IFERROR(VLOOKUP($A5,int_ai_sample!$A$2:$N$101,6,FALSE),"") -> negative | E5: =IFERROR(VLOOKUP($A5,人工標註!$A$2:$N$30,6,FALSE),"") -> negative | F5: =IF(OR(D5="",E5=""),"",IF(D5=E5,"是","否")) -> 是 | G5: =ROUND(COUNTIF($F$2:$F$30,"是")/30,2) -> 0.83 | H5: =IFERROR(IF(VLOOKUP($A5,int_ai_sample!$A$2:$N$101,7,FALSE)=VLOOKUP($A5,人工標註!$A$2:$N$30,7,FALSE),"是","否"),"") -> 是 | I5: =IFERROR(IF(VLOOKUP($A5,int_ai_sample!$A$2:$N$101,8,FALSE)=VLOOKUP($A5,人工標註!$A$2:$N$30,8,FALSE),"是","否"),"") -> 是 | J5: =IFERROR(IF(VLOOKUP($A5,int_ai_sample!$A$2:$N$101,9,FALSE)=VLOOKUP($A5,人工標註!$A$2:$N$30,9,FALSE),"是","否"),"") -> 是 | K5: =IFERROR(IF(VLOOKUP($A5,int_ai_sample!$A$2:$N$101,10,FALSE)=VLOOKUP($A5,人工標註!$A$2:$N$30,10,FALSE),"是","否"),"") -> 是 | L5: =IFERROR(IF(VLOOKUP($A5,int_ai_sample!$A$2:$N$101,11,FALSE)=VLOOKUP($A5,人工標註!$A$2:$N$30,11,FALSE),"是","否"),"") -> 是 | M5: =IFERROR(IF(VLOOKUP($A5,int_ai_sample!$A$2:$N$101,12,FALSE)=VLOOKUP($A5,人工標註!$A$2:$N$30,12,FALSE),"是","否"),"") -> 是 | N5: =IFERROR(IF(VLOOKUP($A5,int_ai_sample!$A$2:$N$101,13,FALSE)=VLOOKUP($A5,人工標註!$A$2:$N$30,13,FALSE),"是","否"),"") -> 是 | O5: =IFERROR(IF(VLOOKUP($A5,int_ai_sample!$A$2:$N$101,14,FALSE)=VLOOKUP($A5,人工標註!$A$2:$N$30,14,FALSE),"是","否"),"") -> 是 | Q5: Topic | R5: TP | S5: FP | T5: FN | U5: TN | V5: Precision | W5: Recall | X5: F1 | Y5: Support
A6: 0c0cb90ec2c6217be6fcfd688817e683 | B6: =IFERROR(VLOOKUP($A6,int_ai_sample!$A$2:$N$101,3,FALSE),"") -> 3 | C6: =IFERROR(VLOOKUP($A6,int_ai_sample!$A$2:$N$101,5,FALSE),"") -> 在指定期限內收到。 | D6: =IFERROR(VLOOKUP($A6,int_ai_sample!$A$2:$N$101,6,FALSE),"") -> positive | E6: =IFERROR(VLOOKUP($A6,人工標註!$A$2:$N$30,6,FALSE),"") -> positive | F6: =IF(OR(D6="",E6=""),"",IF(D6=E6,"是","否")) -> 是 | G6: =ROUND(COUNTIF($F$2:$F$30,"是")/30,2) -> 0.83 | H6: =IFERROR(IF(VLOOKUP($A6,int_ai_sample!$A$2:$N$101,7,FALSE)=VLOOKUP($A6,人工標註!$A$2:$N$30,7,FALSE),"是","否"),"") -> 是 | I6: =IFERROR(IF(VLOOKUP($A6,int_ai_sample!$A$2:$N$101,8,FALSE)=VLOOKUP($A6,人工標註!$A$2:$N$30,8,FALSE),"是","否"),"") -> 是 | J6: =IFERROR(IF(VLOOKUP($A6,int_ai_sample!$A$2:$N$101,9,FALSE)=VLOOKUP($A6,人工標註!$A$2:$N$30,9,FALSE),"是","否"),"") -> 是 | K6: =IFERROR(IF(VLOOKUP($A6,int_ai_sample!$A$2:$N$101,10,FALSE)=VLOOKUP($A6,人工標註!$A$2:$N$30,10,FALSE),"是","否"),"") -> 是 | L6: =IFERROR(IF(VLOOKUP($A6,int_ai_sample!$A$2:$N$101,11,FALSE)=VLOOKUP($A6,人工標註!$A$2:$N$30,11,FALSE),"是","否"),"") -> 是 | M6: =IFERROR(IF(VLOOKUP($A6,int_ai_sample!$A$2:$N$101,12,FALSE)=VLOOKUP($A6,人工標註!$A$2:$N$30,12,FALSE),"是","否"),"") -> 是 | N6: =IFERROR(IF(VLOOKUP($A6,int_ai_sample!$A$2:$N$101,13,FALSE)=VLOOKUP($A6,人工標註!$A$2:$N$30,13,FALSE),"是","否"),"") -> 是 | O6: =IFERROR(IF(VLOOKUP($A6,int_ai_sample!$A$2:$N$101,14,FALSE)=VLOOKUP($A6,人工標註!$A$2:$N$30,14,FALSE),"是","否"),"") -> 是 | Q6: T01 | R6: =COUNTIFS(int_ai_sample!$G$2:$G$30,1,人工標註!$G$2:$G$30,1) -> 17 | S6: =COUNTIFS(int_ai_sample!$G$2:$G$30,1,人工標註!$G$2:$G$30,0) -> 1 | T6: =COUNTIFS(int_ai_sample!$G$2:$G$30,0,人工標註!$G$2:$G$30,1) -> 0 | U6: =COUNTIFS(int_ai_sample!$G$2:$G$30,0,人工標註!$G$2:$G$30,0) -> 11 | V6: =IFERROR(R6/(R6+S6),0) -> 0.94444444 | W6: =IFERROR(R6/(R6+T6),0) -> 1 | X6: =IFERROR(2*V6*W6/(V6+W6),0) -> 0.97142857 | Y6: =R6+T6 -> 17
A7: 0c945ea8559964747662519dbddda79b | B7: =IFERROR(VLOOKUP($A7,int_ai_sample!$A$2:$N$101,3,FALSE),"") -> 1 | C7: =IFERROR(VLOOKUP($A7,int_ai_sample!$A$2:$N$101,5,FALSE),"") -> 我沒有收到商品。 | D7: =IFERROR(VLOOKUP($A7,int_ai_sample!$A$2:$N$101,6,FALSE),"") -> negative | E7: =IFERROR(VLOOKUP($A7,人工標註!$A$2:$N$30,6,FALSE),"") -> negative | F7: =IF(OR(D7="",E7=""),"",IF(D7=E7,"是","否")) -> 是 | G7: =ROUND(COUNTIF($F$2:$F$30,"是")/30,2) -> 0.83 | H7: =IFERROR(IF(VLOOKUP($A7,int_ai_sample!$A$2:$N$101,7,FALSE)=VLOOKUP($A7,人工標註!$A$2:$N$30,7,FALSE),"是","否"),"") -> 是 | I7: =IFERROR(IF(VLOOKUP($A7,int_ai_sample!$A$2:$N$101,8,FALSE)=VLOOKUP($A7,人工標註!$A$2:$N$30,8,FALSE),"是","否"),"") -> 是 | J7: =IFERROR(IF(VLOOKUP($A7,int_ai_sample!$A$2:$N$101,9,FALSE)=VLOOKUP($A7,人工標註!$A$2:$N$30,9,FALSE),"是","否"),"") -> 是 | K7: =IFERROR(IF(VLOOKUP($A7,int_ai_sample!$A$2:$N$101,10,FALSE)=VLOOKUP($A7,人工標註!$A$2:$N$30,10,FALSE),"是","否"),"") -> 是 | L7: =IFERROR(IF(VLOOKUP($A7,int_ai_sample!$A$2:$N$101,11,FALSE)=VLOOKUP($A7,人工標註!$A$2:$N$30,11,FALSE),"是","否"),"") -> 是 | M7: =IFERROR(IF(VLOOKUP($A7,int_ai_sample!$A$2:$N$101,12,FALSE)=VLOOKUP($A7,人工標註!$A$2:$N$30,12,FALSE),"是","否"),"") -> 是 | N7: =IFERROR(IF(VLOOKUP($A7,int_ai_sample!$A$2:$N$101,13,FALSE)=VLOOKUP($A7,人工標註!$A$2:$N$30,13,FALSE),"是","否"),"") -> 是 | O7: =IFERROR(IF(VLOOKUP($A7,int_ai_sample!$A$2:$N$101,14,FALSE)=VLOOKUP($A7,人工標註!$A$2:$N$30,14,FALSE),"是","否"),"") -> 是 | Q7: T02 | R7: =COUNTIFS(int_ai_sample!$H$2:$H$30,1,人工標註!$H$2:$H$30,1) -> 1 | S7: =COUNTIFS(int_ai_sample!$H$2:$H$30,1,人工標註!$H$2:$H$30,0) -> 0 | T7: =COUNTIFS(int_ai_sample!$H$2:$H$30,0,人工標註!$H$2:$H$30,1) -> 3 | U7: =COUNTIFS(int_ai_sample!$H$2:$H$30,0,人工標註!$H$2:$H$30,0) -> 25 | V7: =IFERROR(R7/(R7+S7),0) -> 1 | W7: =IFERROR(R7/(R7+T7),0) -> 0.25 | X7: =IFERROR(2*V7*W7/(V7+W7),0) -> 0.4 | Y7: =R7+T7 -> 4
A8: 0d85b938527456657c1435b3e0cf7726 | B8: =IFERROR(VLOOKUP($A8,int_ai_sample!$A$2:$N$101,3,FALSE),"") -> 4 | C8: =IFERROR(VLOOKUP($A8,int_ai_sample!$A$2:$N$101,5,FALSE),"") -> 很棒，交貨時間很快。 | D8: =IFERROR(VLOOKUP($A8,int_ai_sample!$A$2:$N$101,6,FALSE),"") -> positive | E8: =IFERROR(VLOOKUP($A8,人工標註!$A$2:$N$30,6,FALSE),"") -> positive | F8: =IF(OR(D8="",E8=""),"",IF(D8=E8,"是","否")) -> 是 | G8: =ROUND(COUNTIF($F$2:$F$30,"是")/30,2) -> 0.83 | H8: =IFERROR(IF(VLOOKUP($A8,int_ai_sample!$A$2:$N$101,7,FALSE)=VLOOKUP($A8,人工標註!$A$2:$N$30,7,FALSE),"是","否"),"") -> 是 | I8: =IFERROR(IF(VLOOKUP($A8,int_ai_sample!$A$2:$N$101,8,FALSE)=VLOOKUP($A8,人工標註!$A$2:$N$30,8,FALSE),"是","否"),"") -> 是 | J8: =IFERROR(IF(VLOOKUP($A8,int_ai_sample!$A$2:$N$101,9,FALSE)=VLOOKUP($A8,人工標註!$A$2:$N$30,9,FALSE),"是","否"),"") -> 是 | K8: =IFERROR(IF(VLOOKUP($A8,int_ai_sample!$A$2:$N$101,10,FALSE)=VLOOKUP($A8,人工標註!$A$2:$N$30,10,FALSE),"是","否"),"") -> 是 | L8: =IFERROR(IF(VLOOKUP($A8,int_ai_sample!$A$2:$N$101,11,FALSE)=VLOOKUP($A8,人工標註!$A$2:$N$30,11,FALSE),"是","否"),"") -> 是 | M8: =IFERROR(IF(VLOOKUP($A8,int_ai_sample!$A$2:$N$101,12,FALSE)=VLOOKUP($A8,人工標註!$A$2:$N$30,12,FALSE),"是","否"),"") -> 是 | N8: =IFERROR(IF(VLOOKUP($A8,int_ai_sample!$A$2:$N$101,13,FALSE)=VLOOKUP($A8,人工標註!$A$2:$N$30,13,FALSE),"是","否"),"") -> 是 | O8: =IFERROR(IF(VLOOKUP($A8,int_ai_sample!$A$2:$N$101,14,FALSE)=VLOOKUP($A8,人工標註!$A$2:$N$30,14,FALSE),"是","否"),"") -> 是 | Q8: T03 | R8: =COUNTIFS(int_ai_sample!$I$2:$I$30,1,人工標註!$I$2:$I$30,1) -> 4 | S8: =COUNTIFS(int_ai_sample!$I$2:$I$30,1,人工標註!$I$2:$I$30,0) -> 3 | T8: =COUNTIFS(int_ai_sample!$I$2:$I$30,0,人工標註!$I$2:$I$30,1) -> 2 | U8: =COUNTIFS(int_ai_sample!$I$2:$I$30,0,人工標註!$I$2:$I$30,0) -> 20 | V8: =IFERROR(R8/(R8+S8),0) -> 0.57142857 | W8: =IFERROR(R8/(R8+T8),0) -> 0.66666667 | X8: =IFERROR(2*V8*W8/(V8+W8),0) -> 0.61538462 | Y8: =R8+T8 -> 6
A9: 0f508c7aba0bbe43ee80975436fd3d5d | B9: =IFERROR(VLOOKUP($A9,int_ai_sample!$A$2:$N$101,3,FALSE),"") -> 4 | C9: =IFERROR(VLOOKUP($A9,int_ai_sample!$A$2:$N$101,5,FALSE),"") -> 商品送達正確而且很快。已經測試過並通過驗收。建議加強塑膠結構，特別是曲柄塔，讓動作更穩固。謝謝。 | D9: =IFERROR(VLOOKUP($A9,int_ai_sample!$A$2:$N$101,6,FALSE),"") -> positive | E9: =IFERROR(VLOOKUP($A9,人工標註!$A$2:$N$30,6,FALSE),"") -> mixed | F9: =IF(OR(D9="",E9=""),"",IF(D9=E9,"是","否")) -> 否 | G9: =ROUND(COUNTIF($F$2:$F$30,"是")/30,2) -> 0.83 | H9: =IFERROR(IF(VLOOKUP($A9,int_ai_sample!$A$2:$N$101,7,FALSE)=VLOOKUP($A9,人工標註!$A$2:$N$30,7,FALSE),"是","否"),"") -> 是 | I9: =IFERROR(IF(VLOOKUP($A9,int_ai_sample!$A$2:$N$101,8,FALSE)=VLOOKUP($A9,人工標註!$A$2:$N$30,8,FALSE),"是","否"),"") -> 是 | J9: =IFERROR(IF(VLOOKUP($A9,int_ai_sample!$A$2:$N$101,9,FALSE)=VLOOKUP($A9,人工標註!$A$2:$N$30,9,FALSE),"是","否"),"") -> 是 | K9: =IFERROR(IF(VLOOKUP($A9,int_ai_sample!$A$2:$N$101,10,FALSE)=VLOOKUP($A9,人工標註!$A$2:$N$30,10,FALSE),"是","否"),"") -> 是 | L9: =IFERROR(IF(VLOOKUP($A9,int_ai_sample!$A$2:$N$101,11,FALSE)=VLOOKUP($A9,人工標註!$A$2:$N$30,11,FALSE),"是","否"),"") -> 是 | M9: =IFERROR(IF(VLOOKUP($A9,int_ai_sample!$A$2:$N$101,12,FALSE)=VLOOKUP($A9,人工標註!$A$2:$N$30,12,FALSE),"是","否"),"") -> 是 | N9: =IFERROR(IF(VLOOKUP($A9,int_ai_sample!$A$2:$N$101,13,FALSE)=VLOOKUP($A9,人工標註!$A$2:$N$30,13,FALSE),"是","否"),"") -> 是 | O9: =IFERROR(IF(VLOOKUP($A9,int_ai_sample!$A$2:$N$101,14,FALSE)=VLOOKUP($A9,人工標註!$A$2:$N$30,14,FALSE),"是","否"),"") -> 是 | Q9: T04 | R9: =COUNTIFS(int_ai_sample!$J$2:$J$30,1,人工標註!$J$2:$J$30,1) -> 2 | S9: =COUNTIFS(int_ai_sample!$J$2:$J$30,1,人工標註!$J$2:$J$30,0) -> 1 | T9: =COUNTIFS(int_ai_sample!$J$2:$J$30,0,人工標註!$J$2:$J$30,1) -> 1 | U9: =COUNTIFS(int_ai_sample!$J$2:$J$30,0,人工標註!$J$2:$J$30,0) -> 25 | V9: =IFERROR(R9/(R9+S9),0) -> 0.66666667 | W9: =IFERROR(R9/(R9+T9),0) -> 0.66666667 | X9: =IFERROR(2*V9*W9/(V9+W9),0) -> 0.66666667 | Y9: =R9+T9 -> 3
A10: 10460eaad2a97e45e5735e7058d778b3 | B10: =IFERROR(VLOOKUP($A10,int_ai_sample!$A$2:$N$101,3,FALSE),"") -> 3 | C10: =IFERROR(VLOOKUP($A10,int_ai_sample!$A$2:$N$101,5,FALSE),"") -> 商品看起來像二手，logo 的漆都磨掉了，還有一些刮痕。不要想省 5 塊錢而買這家店的東西。 | D10: =IFERROR(VLOOKUP($A10,int_ai_sample!$A$2:$N$101,6,FALSE),"") -> negative | E10: =IFERROR(VLOOKUP($A10,人工標註!$A$2:$N$30,6,FALSE),"") -> negative | F10: =IF(OR(D10="",E10=""),"",IF(D10=E10,"是","否")) -> 是 | G10: =ROUND(COUNTIF($F$2:$F$30,"是")/30,2) -> 0.83 | H10: =IFERROR(IF(VLOOKUP($A10,int_ai_sample!$A$2:$N$101,7,FALSE)=VLOOKUP($A10,人工標註!$A$2:$N$30,7,FALSE),"是","否"),"") -> 是 | I10: =IFERROR(IF(VLOOKUP($A10,int_ai_sample!$A$2:$N$101,8,FALSE)=VLOOKUP($A10,人工標註!$A$2:$N$30,8,FALSE),"是","否"),"") -> 是 | J10: =IFERROR(IF(VLOOKUP($A10,int_ai_sample!$A$2:$N$101,9,FALSE)=VLOOKUP($A10,人工標註!$A$2:$N$30,9,FALSE),"是","否"),"") -> 是 | K10: =IFERROR(IF(VLOOKUP($A10,int_ai_sample!$A$2:$N$101,10,FALSE)=VLOOKUP($A10,人工標註!$A$2:$N$30,10,FALSE),"是","否"),"") -> 是 | L10: =IFERROR(IF(VLOOKUP($A10,int_ai_sample!$A$2:$N$101,11,FALSE)=VLOOKUP($A10,人工標註!$A$2:$N$30,11,FALSE),"是","否"),"") -> 是 | M10: =IFERROR(IF(VLOOKUP($A10,int_ai_sample!$A$2:$N$101,12,FALSE)=VLOOKUP($A10,人工標註!$A$2:$N$30,12,FALSE),"是","否"),"") -> 是 | N10: =IFERROR(IF(VLOOKUP($A10,int_ai_sample!$A$2:$N$101,13,FALSE)=VLOOKUP($A10,人工標註!$A$2:$N$30,13,FALSE),"是","否"),"") -> 是 | O10: =IFERROR(IF(VLOOKUP($A10,int_ai_sample!$A$2:$N$101,14,FALSE)=VLOOKUP($A10,人工標註!$A$2:$N$30,14,FALSE),"是","否"),"") -> 是 | Q10: T05 | R10: =COUNTIFS(int_ai_sample!$K$2:$K$30,1,人工標註!$K$2:$K$30,1) -> 0 | S10: =COUNTIFS(int_ai_sample!$K$2:$K$30,1,人工標註!$K$2:$K$30,0) -> 0 | T10: =COUNTIFS(int_ai_sample!$K$2:$K$30,0,人工標註!$K$2:$K$30,1) -> 0 | U10: =COUNTIFS(int_ai_sample!$K$2:$K$30,0,人工標註!$K$2:$K$30,0) -> 29 | V10: =IFERROR(R10/(R10+S10),0) -> 0 | W10: =IFERROR(R10/(R10+T10),0) -> 0 | X10: =IFERROR(2*V10*W10/(V10+W10),0) -> 0 | Y10: =R10+T10 -> 0
A11: 1110fd4c2db3d0f9df542b46aebcbfbd | B11: =IFERROR(VLOOKUP($A11,int_ai_sample!$A$2:$N$101,3,FALSE),"") -> 5 | C11: =IFERROR(VLOOKUP($A11,int_ai_sample!$A$2:$N$101,5,FALSE),"") -> 下午好……我有收到商品，但保溫便當包的提把出問題了，線縫脫開了。我該怎麼換？ | D11: =IFERROR(VLOOKUP($A11,int_ai_sample!$A$2:$N$101,6,FALSE),"") -> negative | E11: =IFERROR(VLOOKUP($A11,人工標註!$A$2:$N$30,6,FALSE),"") -> negative | F11: =IF(OR(D11="",E11=""),"",IF(D11=E11,"是","否")) -> 是 | G11: =ROUND(COUNTIF($F$2:$F$30,"是")/30,2) -> 0.83 | H11: =IFERROR(IF(VLOOKUP($A11,int_ai_sample!$A$2:$N$101,7,FALSE)=VLOOKUP($A11,人工標註!$A$2:$N$30,7,FALSE),"是","否"),"") -> 是 | I11: =IFERROR(IF(VLOOKUP($A11,int_ai_sample!$A$2:$N$101,8,FALSE)=VLOOKUP($A11,人工標註!$A$2:$N$30,8,FALSE),"是","否"),"") -> 是 | J11: =IFERROR(IF(VLOOKUP($A11,int_ai_sample!$A$2:$N$101,9,FALSE)=VLOOKUP($A11,人工標註!$A$2:$N$30,9,FALSE),"是","否"),"") -> 是 | K11: =IFERROR(IF(VLOOKUP($A11,int_ai_sample!$A$2:$N$101,10,FALSE)=VLOOKUP($A11,人工標註!$A$2:$N$30,10,FALSE),"是","否"),"") -> 是 | L11: =IFERROR(IF(VLOOKUP($A11,int_ai_sample!$A$2:$N$101,11,FALSE)=VLOOKUP($A11,人工標註!$A$2:$N$30,11,FALSE),"是","否"),"") -> 是 | M11: =IFERROR(IF(VLOOKUP($A11,int_ai_sample!$A$2:$N$101,12,FALSE)=VLOOKUP($A11,人工標註!$A$2:$N$30,12,FALSE),"是","否"),"") -> 否 | N11: =IFERROR(IF(VLOOKUP($A11,int_ai_sample!$A$2:$N$101,13,FALSE)=VLOOKUP($A11,人工標註!$A$2:$N$30,13,FALSE),"是","否"),"") -> 是 | O11: =IFERROR(IF(VLOOKUP($A11,int_ai_sample!$A$2:$N$101,14,FALSE)=VLOOKUP($A11,人工標註!$A$2:$N$30,14,FALSE),"是","否"),"") -> 是 | Q11: T06 | R11: =COUNTIFS(int_ai_sample!$L$2:$L$30,1,人工標註!$L$2:$L$30,1) -> 1 | S11: =COUNTIFS(int_ai_sample!$L$2:$L$30,1,人工標註!$L$2:$L$30,0) -> 3 | T11: =COUNTIFS(int_ai_sample!$L$2:$L$30,0,人工標註!$L$2:$L$30,1) -> 0 | U11: =COUNTIFS(int_ai_sample!$L$2:$L$30,0,人工標註!$L$2:$L$30,0) -> 25 | V11: =IFERROR(R11/(R11+S11),0) -> 0.25 | W11: =IFERROR(R11/(R11+T11),0) -> 1 | X11: =IFERROR(2*V11*W11/(V11+W11),0) -> 0.4 | Y11: =R11+T11 -> 1
A12: 14bd0f4bea843699f4da3b65e10cccae | B12: =IFERROR(VLOOKUP($A12,int_ai_sample!$A$2:$N$101,3,FALSE),"") -> 4 | C12: =IFERROR(VLOOKUP($A12,int_ai_sample!$A$2:$N$101,5,FALSE),"") -> 比預期更早到貨，運費比 lannister 的更貴。看起來非常不錯，前幾次踩踏的感覺很好。但沒有附說明手冊，不過組裝很容易也很直覺。 | D12: =IFERROR(VLOOKUP($A12,int_ai_sample!$A$2:$N$101,6,FALSE),"") -> mixed | E12: =IFERROR(VLOOKUP($A12,人工標註!$A$2:$N$30,6,FALSE),"") -> mixed | F12: =IF(OR(D12="",E12=""),"",IF(D12=E12,"是","否")) -> 是 | G12: =ROUND(COUNTIF($F$2:$F$30,"是")/30,2) -> 0.83 | H12: =IFERROR(IF(VLOOKUP($A12,int_ai_sample!$A$2:$N$101,7,FALSE)=VLOOKUP($A12,人工標註!$A$2:$N$30,7,FALSE),"是","否"),"") -> 是 | I12: =IFERROR(IF(VLOOKUP($A12,int_ai_sample!$A$2:$N$101,8,FALSE)=VLOOKUP($A12,人工標註!$A$2:$N$30,8,FALSE),"是","否"),"") -> 是 | J12: =IFERROR(IF(VLOOKUP($A12,int_ai_sample!$A$2:$N$101,9,FALSE)=VLOOKUP($A12,人工標註!$A$2:$N$30,9,FALSE),"是","否"),"") -> 否 | K12: =IFERROR(IF(VLOOKUP($A12,int_ai_sample!$A$2:$N$101,10,FALSE)=VLOOKUP($A12,人工標註!$A$2:$N$30,10,FALSE),"是","否"),"") -> 是 | L12: =IFERROR(IF(VLOOKUP($A12,int_ai_sample!$A$2:$N$101,11,FALSE)=VLOOKUP($A12,人工標註!$A$2:$N$30,11,FALSE),"是","否"),"") -> 是 | M12: =IFERROR(IF(VLOOKUP($A12,int_ai_sample!$A$2:$N$101,12,FALSE)=VLOOKUP($A12,人工標註!$A$2:$N$30,12,FALSE),"是","否"),"") -> 是 | N12: =IFERROR(IF(VLOOKUP($A12,int_ai_sample!$A$2:$N$101,13,FALSE)=VLOOKUP($A12,人工標註!$A$2:$N$30,13,FALSE),"是","否"),"") -> 是 | O12: =IFERROR(IF(VLOOKUP($A12,int_ai_sample!$A$2:$N$101,14,FALSE)=VLOOKUP($A12,人工標註!$A$2:$N$30,14,FALSE),"是","否"),"") -> 是 | Q12: T07 | R12: =COUNTIFS(int_ai_sample!$M$2:$M$30,1,人工標註!$M$2:$M$30,1) -> 1 | S12: =COUNTIFS(int_ai_sample!$M$2:$M$30,1,人工標註!$M$2:$M$30,0) -> 0 | T12: =COUNTIFS(int_ai_sample!$M$2:$M$30,0,人工標註!$M$2:$M$30,1) -> 0 | U12: =COUNTIFS(int_ai_sample!$M$2:$M$30,0,人工標註!$M$2:$M$30,0) -> 28 | V12: =IFERROR(R12/(R12+S12),0) -> 1 | W12: =IFERROR(R12/(R12+T12),0) -> 1 | X12: =IFERROR(2*V12*W12/(V12+W12),0) -> 1 | Y12: =R12+T12 -> 1
A13: 1e8f7bf12393c8879303b37abf5e58fb | B13: =IFERROR(VLOOKUP($A13,int_ai_sample!$A$2:$N$101,3,FALSE),"") -> 1 | C13: =IFERROR(VLOOKUP($A13,int_ai_sample!$A$2:$N$101,5,FALSE),"") -> 我訂的是一個商品，但送來的卻是另一個。對方說會再寄正確的，但我現在還在等。 | D13: =IFERROR(VLOOKUP($A13,int_ai_sample!$A$2:$N$101,6,FALSE),"") -> negative | E13: =IFERROR(VLOOKUP($A13,人工標註!$A$2:$N$30,6,FALSE),"") -> negative | F13: =IF(OR(D13="",E13=""),"",IF(D13=E13,"是","否")) -> 是 | G13: =ROUND(COUNTIF($F$2:$F$30,"是")/30,2) -> 0.83 | H13: =IFERROR(IF(VLOOKUP($A13,int_ai_sample!$A$2:$N$101,7,FALSE)=VLOOKUP($A13,人工標註!$A$2:$N$30,7,FALSE),"是","否"),"") -> 是 | I13: =IFERROR(IF(VLOOKUP($A13,int_ai_sample!$A$2:$N$101,8,FALSE)=VLOOKUP($A13,人工標註!$A$2:$N$30,8,FALSE),"是","否"),"") -> 是 | J13: =IFERROR(IF(VLOOKUP($A13,int_ai_sample!$A$2:$N$101,9,FALSE)=VLOOKUP($A13,人工標註!$A$2:$N$30,9,FALSE),"是","否"),"") -> 是 | K13: =IFERROR(IF(VLOOKUP($A13,int_ai_sample!$A$2:$N$101,10,FALSE)=VLOOKUP($A13,人工標註!$A$2:$N$30,10,FALSE),"是","否"),"") -> 是 | L13: =IFERROR(IF(VLOOKUP($A13,int_ai_sample!$A$2:$N$101,11,FALSE)=VLOOKUP($A13,人工標註!$A$2:$N$30,11,FALSE),"是","否"),"") -> 是 | M13: =IFERROR(IF(VLOOKUP($A13,int_ai_sample!$A$2:$N$101,12,FALSE)=VLOOKUP($A13,人工標註!$A$2:$N$30,12,FALSE),"是","否"),"") -> 否 | N13: =IFERROR(IF(VLOOKUP($A13,int_ai_sample!$A$2:$N$101,13,FALSE)=VLOOKUP($A13,人工標註!$A$2:$N$30,13,FALSE),"是","否"),"") -> 是 | O13: =IFERROR(IF(VLOOKUP($A13,int_ai_sample!$A$2:$N$101,14,FALSE)=VLOOKUP($A13,人工標註!$A$2:$N$30,14,FALSE),"是","否"),"") -> 是 | Q13: T08 | R13: =COUNTIFS(int_ai_sample!$N$2:$N$30,1,人工標註!$N$2:$N$30,1) -> 0 | S13: =COUNTIFS(int_ai_sample!$N$2:$N$30,1,人工標註!$N$2:$N$30,0) -> 0 | T13: =COUNTIFS(int_ai_sample!$N$2:$N$30,0,人工標註!$N$2:$N$30,1) -> 0 | U13: =COUNTIFS(int_ai_sample!$N$2:$N$30,0,人工標註!$N$2:$N$30,0) -> 29 | V13: =IFERROR(R13/(R13+S13),0) -> 0 | W13: =IFERROR(R13/(R13+T13),0) -> 0 | X13: =IFERROR(2*V13*W13/(V13+W13),0) -> 0 | Y13: =R13+T13 -> 0
A14: 1f58fdeec8f079e90b3d2d7f64b87c59 | B14: =IFERROR(VLOOKUP($A14,int_ai_sample!$A$2:$N$101,3,FALSE),"") -> 5 | C14: =IFERROR(VLOOKUP($A14,int_ai_sample!$A$2:$N$101,5,FALSE),"") -> 很好，很好。店家在期限內送貨。 | D14: =IFERROR(VLOOKUP($A14,int_ai_sample!$A$2:$N$101,6,FALSE),"") -> positive | E14: =IFERROR(VLOOKUP($A14,人工標註!$A$2:$N$30,6,FALSE),"") -> positive | F14: =IF(OR(D14="",E14=""),"",IF(D14=E14,"是","否")) -> 是 | G14: =ROUND(COUNTIF($F$2:$F$30,"是")/30,2) -> 0.83 | H14: =IFERROR(IF(VLOOKUP($A14,int_ai_sample!$A$2:$N$101,7,FALSE)=VLOOKUP($A14,人工標註!$A$2:$N$30,7,FALSE),"是","否"),"") -> 是 | I14: =IFERROR(IF(VLOOKUP($A14,int_ai_sample!$A$2:$N$101,8,FALSE)=VLOOKUP($A14,人工標註!$A$2:$N$30,8,FALSE),"是","否"),"") -> 是 | J14: =IFERROR(IF(VLOOKUP($A14,int_ai_sample!$A$2:$N$101,9,FALSE)=VLOOKUP($A14,人工標註!$A$2:$N$30,9,FALSE),"是","否"),"") -> 是 | K14: =IFERROR(IF(VLOOKUP($A14,int_ai_sample!$A$2:$N$101,10,FALSE)=VLOOKUP($A14,人工標註!$A$2:$N$30,10,FALSE),"是","否"),"") -> 是 | L14: =IFERROR(IF(VLOOKUP($A14,int_ai_sample!$A$2:$N$101,11,FALSE)=VLOOKUP($A14,人工標註!$A$2:$N$30,11,FALSE),"是","否"),"") -> 是 | M14: =IFERROR(IF(VLOOKUP($A14,int_ai_sample!$A$2:$N$101,12,FALSE)=VLOOKUP($A14,人工標註!$A$2:$N$30,12,FALSE),"是","否"),"") -> 是 | N14: =IFERROR(IF(VLOOKUP($A14,int_ai_sample!$A$2:$N$101,13,FALSE)=VLOOKUP($A14,人工標註!$A$2:$N$30,13,FALSE),"是","否"),"") -> 是 | O14: =IFERROR(IF(VLOOKUP($A14,int_ai_sample!$A$2:$N$101,14,FALSE)=VLOOKUP($A14,人工標註!$A$2:$N$30,14,FALSE),"是","否"),"") -> 是
A15: 21a40d6b28216d468ca32122e41cee68 | B15: =IFERROR(VLOOKUP($A15,int_ai_sample!$A$2:$N$101,3,FALSE),"") -> 2 | C15: =IFERROR(VLOOKUP($A15,int_ai_sample!$A$2:$N$101,5,FALSE),"") -> 沒有任何說明就把訂單取消了。 | D15: =IFERROR(VLOOKUP($A15,int_ai_sample!$A$2:$N$101,6,FALSE),"") -> negative | E15: =IFERROR(VLOOKUP($A15,人工標註!$A$2:$N$30,6,FALSE),"") -> negative | F15: =IF(OR(D15="",E15=""),"",IF(D15=E15,"是","否")) -> 是 | G15: =ROUND(COUNTIF($F$2:$F$30,"是")/30,2) -> 0.83 | H15: =IFERROR(IF(VLOOKUP($A15,int_ai_sample!$A$2:$N$101,7,FALSE)=VLOOKUP($A15,人工標註!$A$2:$N$30,7,FALSE),"是","否"),"") -> 是 | I15: =IFERROR(IF(VLOOKUP($A15,int_ai_sample!$A$2:$N$101,8,FALSE)=VLOOKUP($A15,人工標註!$A$2:$N$30,8,FALSE),"是","否"),"") -> 否 | J15: =IFERROR(IF(VLOOKUP($A15,int_ai_sample!$A$2:$N$101,9,FALSE)=VLOOKUP($A15,人工標註!$A$2:$N$30,9,FALSE),"是","否"),"") -> 是 | K15: =IFERROR(IF(VLOOKUP($A15,int_ai_sample!$A$2:$N$101,10,FALSE)=VLOOKUP($A15,人工標註!$A$2:$N$30,10,FALSE),"是","否"),"") -> 是 | L15: =IFERROR(IF(VLOOKUP($A15,int_ai_sample!$A$2:$N$101,11,FALSE)=VLOOKUP($A15,人工標註!$A$2:$N$30,11,FALSE),"是","否"),"") -> 是 | M15: =IFERROR(IF(VLOOKUP($A15,int_ai_sample!$A$2:$N$101,12,FALSE)=VLOOKUP($A15,人工標註!$A$2:$N$30,12,FALSE),"是","否"),"") -> 是 | N15: =IFERROR(IF(VLOOKUP($A15,int_ai_sample!$A$2:$N$101,13,FALSE)=VLOOKUP($A15,人工標註!$A$2:$N$30,13,FALSE),"是","否"),"") -> 是 | O15: =IFERROR(IF(VLOOKUP($A15,int_ai_sample!$A$2:$N$101,14,FALSE)=VLOOKUP($A15,人工標註!$A$2:$N$30,14,FALSE),"是","否"),"") -> 是 | Q15: Macro avg | V15: =AVERAGE(V6:V13) -> 0.55406746 | W15: =AVERAGE(W6:W13) -> 0.57291667 | X15: =AVERAGE(X6:X13) -> 0.50668498 | Y15: =SUM(Y6:Y13) -> 32
A16: 24e467c8784b125c2822e0f9e6bd877f | B16: =IFERROR(VLOOKUP($A16,int_ai_sample!$A$2:$N$101,3,FALSE),"") -> 2 | C16: =IFERROR(VLOOKUP($A16,int_ai_sample!$A$2:$N$101,5,FALSE),"") -> 商品沒有送到！ | D16: =IFERROR(VLOOKUP($A16,int_ai_sample!$A$2:$N$101,6,FALSE),"") -> negative | E16: =IFERROR(VLOOKUP($A16,人工標註!$A$2:$N$30,6,FALSE),"") -> negative | F16: =IF(OR(D16="",E16=""),"",IF(D16=E16,"是","否")) -> 是 | G16: =ROUND(COUNTIF($F$2:$F$30,"是")/30,2) -> 0.83 | H16: =IFERROR(IF(VLOOKUP($A16,int_ai_sample!$A$2:$N$101,7,FALSE)=VLOOKUP($A16,人工標註!$A$2:$N$30,7,FALSE),"是","否"),"") -> 是 | I16: =IFERROR(IF(VLOOKUP($A16,int_ai_sample!$A$2:$N$101,8,FALSE)=VLOOKUP($A16,人工標註!$A$2:$N$30,8,FALSE),"是","否"),"") -> 是 | J16: =IFERROR(IF(VLOOKUP($A16,int_ai_sample!$A$2:$N$101,9,FALSE)=VLOOKUP($A16,人工標註!$A$2:$N$30,9,FALSE),"是","否"),"") -> 是 | K16: =IFERROR(IF(VLOOKUP($A16,int_ai_sample!$A$2:$N$101,10,FALSE)=VLOOKUP($A16,人工標註!$A$2:$N$30,10,FALSE),"是","否"),"") -> 是 | L16: =IFERROR(IF(VLOOKUP($A16,int_ai_sample!$A$2:$N$101,11,FALSE)=VLOOKUP($A16,人工標註!$A$2:$N$30,11,FALSE),"是","否"),"") -> 是 | M16: =IFERROR(IF(VLOOKUP($A16,int_ai_sample!$A$2:$N$101,12,FALSE)=VLOOKUP($A16,人工標註!$A$2:$N$30,12,FALSE),"是","否"),"") -> 是 | N16: =IFERROR(IF(VLOOKUP($A16,int_ai_sample!$A$2:$N$101,13,FALSE)=VLOOKUP($A16,人工標註!$A$2:$N$30,13,FALSE),"是","否"),"") -> 是 | O16: =IFERROR(IF(VLOOKUP($A16,int_ai_sample!$A$2:$N$101,14,FALSE)=VLOOKUP($A16,人工標註!$A$2:$N$30,14,FALSE),"是","否"),"") -> 是 | Q16: Micro avg | R16: =SUM(R6:R13) -> 26 | S16: =SUM(S6:S13) -> 8 | T16: =SUM(T6:T13) -> 6 | U16: =SUM(U6:U13) -> 192 | V16: =IFERROR(R16/(R16+S16),0) -> 0.76470588 | W16: =IFERROR(R16/(R16+T16),0) -> 0.8125 | X16: =IFERROR(2*V16*W16/(V16+W16),0) -> 0.78787879 | Y16: =SUM(Y6:Y13) -> 32
A17: 2518ac1e2962f0f7df21e07966423779 | B17: =IFERROR(VLOOKUP($A17,int_ai_sample!$A$2:$N$101,3,FALSE),"") -> 1 | C17: =IFERROR(VLOOKUP($A17,int_ai_sample!$A$2:$N$101,5,FALSE),"") -> 商品已經超過預定送達期限。 | D17: =IFERROR(VLOOKUP($A17,int_ai_sample!$A$2:$N$101,6,FALSE),"") -> negative | E17: =IFERROR(VLOOKUP($A17,人工標註!$A$2:$N$30,6,FALSE),"") -> negative | F17: =IF(OR(D17="",E17=""),"",IF(D17=E17,"是","否")) -> 是 | G17: =ROUND(COUNTIF($F$2:$F$30,"是")/30,2) -> 0.83 | H17: =IFERROR(IF(VLOOKUP($A17,int_ai_sample!$A$2:$N$101,7,FALSE)=VLOOKUP($A17,人工標註!$A$2:$N$30,7,FALSE),"是","否"),"") -> 是 | I17: =IFERROR(IF(VLOOKUP($A17,int_ai_sample!$A$2:$N$101,8,FALSE)=VLOOKUP($A17,人工標註!$A$2:$N$30,8,FALSE),"是","否"),"") -> 是 | J17: =IFERROR(IF(VLOOKUP($A17,int_ai_sample!$A$2:$N$101,9,FALSE)=VLOOKUP($A17,人工標註!$A$2:$N$30,9,FALSE),"是","否"),"") -> 是 | K17: =IFERROR(IF(VLOOKUP($A17,int_ai_sample!$A$2:$N$101,10,FALSE)=VLOOKUP($A17,人工標註!$A$2:$N$30,10,FALSE),"是","否"),"") -> 是 | L17: =IFERROR(IF(VLOOKUP($A17,int_ai_sample!$A$2:$N$101,11,FALSE)=VLOOKUP($A17,人工標註!$A$2:$N$30,11,FALSE),"是","否"),"") -> 是 | M17: =IFERROR(IF(VLOOKUP($A17,int_ai_sample!$A$2:$N$101,12,FALSE)=VLOOKUP($A17,人工標註!$A$2:$N$30,12,FALSE),"是","否"),"") -> 是 | N17: =IFERROR(IF(VLOOKUP($A17,int_ai_sample!$A$2:$N$101,13,FALSE)=VLOOKUP($A17,人工標註!$A$2:$N$30,13,FALSE),"是","否"),"") -> 是 | O17: =IFERROR(IF(VLOOKUP($A17,int_ai_sample!$A$2:$N$101,14,FALSE)=VLOOKUP($A17,人工標註!$A$2:$N$30,14,FALSE),"是","否"),"") -> 是
A18: 257d0c7bb5767c7bd21463a68e5ff064 | B18: =IFERROR(VLOOKUP($A18,int_ai_sample!$A$2:$N$101,3,FALSE),"") -> 5 | C18: =IFERROR(VLOOKUP($A18,int_ai_sample!$A$2:$N$101,5,FALSE),"") -> 賣家很好，商品也很好!! | D18: =IFERROR(VLOOKUP($A18,int_ai_sample!$A$2:$N$101,6,FALSE),"") -> positive | E18: =IFERROR(VLOOKUP($A18,人工標註!$A$2:$N$30,6,FALSE),"") -> positive | F18: =IF(OR(D18="",E18=""),"",IF(D18=E18,"是","否")) -> 是 | G18: =ROUND(COUNTIF($F$2:$F$30,"是")/30,2) -> 0.83 | H18: =IFERROR(IF(VLOOKUP($A18,int_ai_sample!$A$2:$N$101,7,FALSE)=VLOOKUP($A18,人工標註!$A$2:$N$30,7,FALSE),"是","否"),"") -> 是 | I18: =IFERROR(IF(VLOOKUP($A18,int_ai_sample!$A$2:$N$101,8,FALSE)=VLOOKUP($A18,人工標註!$A$2:$N$30,8,FALSE),"是","否"),"") -> 是 | J18: =IFERROR(IF(VLOOKUP($A18,int_ai_sample!$A$2:$N$101,9,FALSE)=VLOOKUP($A18,人工標註!$A$2:$N$30,9,FALSE),"是","否"),"") -> 否 | K18: =IFERROR(IF(VLOOKUP($A18,int_ai_sample!$A$2:$N$101,10,FALSE)=VLOOKUP($A18,人工標註!$A$2:$N$30,10,FALSE),"是","否"),"") -> 是 | L18: =IFERROR(IF(VLOOKUP($A18,int_ai_sample!$A$2:$N$101,11,FALSE)=VLOOKUP($A18,人工標註!$A$2:$N$30,11,FALSE),"是","否"),"") -> 是 | M18: =IFERROR(IF(VLOOKUP($A18,int_ai_sample!$A$2:$N$101,12,FALSE)=VLOOKUP($A18,人工標註!$A$2:$N$30,12,FALSE),"是","否"),"") -> 否 | N18: =IFERROR(IF(VLOOKUP($A18,int_ai_sample!$A$2:$N$101,13,FALSE)=VLOOKUP($A18,人工標註!$A$2:$N$30,13,FALSE),"是","否"),"") -> 是 | O18: =IFERROR(IF(VLOOKUP($A18,int_ai_sample!$A$2:$N$101,14,FALSE)=VLOOKUP($A18,人工標註!$A$2:$N$30,14,FALSE),"是","否"),"") -> 是
A19: 27a5cc5b3fbe60cd8a988c1b869af369 | B19: =IFERROR(VLOOKUP($A19,int_ai_sample!$A$2:$N$101,3,FALSE),"") -> 4 | C19: =IFERROR(VLOOKUP($A19,int_ai_sample!$A$2:$N$101,5,FALSE),"") -> 很討厭的是我得跑去郵局領貨。就算我不住在風險區域也一樣。 | D19: =IFERROR(VLOOKUP($A19,int_ai_sample!$A$2:$N$101,6,FALSE),"") -> negative | E19: =IFERROR(VLOOKUP($A19,人工標註!$A$2:$N$30,6,FALSE),"") -> negative | F19: =IF(OR(D19="",E19=""),"",IF(D19=E19,"是","否")) -> 是 | G19: =ROUND(COUNTIF($F$2:$F$30,"是")/30,2) -> 0.83 | H19: =IFERROR(IF(VLOOKUP($A19,int_ai_sample!$A$2:$N$101,7,FALSE)=VLOOKUP($A19,人工標註!$A$2:$N$30,7,FALSE),"是","否"),"") -> 是 | I19: =IFERROR(IF(VLOOKUP($A19,int_ai_sample!$A$2:$N$101,8,FALSE)=VLOOKUP($A19,人工標註!$A$2:$N$30,8,FALSE),"是","否"),"") -> 是 | J19: =IFERROR(IF(VLOOKUP($A19,int_ai_sample!$A$2:$N$101,9,FALSE)=VLOOKUP($A19,人工標註!$A$2:$N$30,9,FALSE),"是","否"),"") -> 是 | K19: =IFERROR(IF(VLOOKUP($A19,int_ai_sample!$A$2:$N$101,10,FALSE)=VLOOKUP($A19,人工標註!$A$2:$N$30,10,FALSE),"是","否"),"") -> 是 | L19: =IFERROR(IF(VLOOKUP($A19,int_ai_sample!$A$2:$N$101,11,FALSE)=VLOOKUP($A19,人工標註!$A$2:$N$30,11,FALSE),"是","否"),"") -> 是 | M19: =IFERROR(IF(VLOOKUP($A19,int_ai_sample!$A$2:$N$101,12,FALSE)=VLOOKUP($A19,人工標註!$A$2:$N$30,12,FALSE),"是","否"),"") -> 是 | N19: =IFERROR(IF(VLOOKUP($A19,int_ai_sample!$A$2:$N$101,13,FALSE)=VLOOKUP($A19,人工標註!$A$2:$N$30,13,FALSE),"是","否"),"") -> 是 | O19: =IFERROR(IF(VLOOKUP($A19,int_ai_sample!$A$2:$N$101,14,FALSE)=VLOOKUP($A19,人工標註!$A$2:$N$30,14,FALSE),"是","否"),"") -> 是
A20: 2b6649bd0a6f3d3370377e5cbfe7d256 | B20: =IFERROR(VLOOKUP($A20,int_ai_sample!$A$2:$N$101,3,FALSE),"") -> 1 | C20: =IFERROR(VLOOKUP($A20,int_ai_sample!$A$2:$N$101,5,FALSE),"") -> 我得去郵局取件；他們沒有通知我還得特地跑一趟，而且也沒有送到家裡。 | D20: =IFERROR(VLOOKUP($A20,int_ai_sample!$A$2:$N$101,6,FALSE),"") -> negative | E20: =IFERROR(VLOOKUP($A20,人工標註!$A$2:$N$30,6,FALSE),"") -> negative | F20: =IF(OR(D20="",E20=""),"",IF(D20=E20,"是","否")) -> 是 | G20: =ROUND(COUNTIF($F$2:$F$30,"是")/30,2) -> 0.83 | H20: =IFERROR(IF(VLOOKUP($A20,int_ai_sample!$A$2:$N$101,7,FALSE)=VLOOKUP($A20,人工標註!$A$2:$N$30,7,FALSE),"是","否"),"") -> 是 | I20: =IFERROR(IF(VLOOKUP($A20,int_ai_sample!$A$2:$N$101,8,FALSE)=VLOOKUP($A20,人工標註!$A$2:$N$30,8,FALSE),"是","否"),"") -> 是 | J20: =IFERROR(IF(VLOOKUP($A20,int_ai_sample!$A$2:$N$101,9,FALSE)=VLOOKUP($A20,人工標註!$A$2:$N$30,9,FALSE),"是","否"),"") -> 是 | K20: =IFERROR(IF(VLOOKUP($A20,int_ai_sample!$A$2:$N$101,10,FALSE)=VLOOKUP($A20,人工標註!$A$2:$N$30,10,FALSE),"是","否"),"") -> 是 | L20: =IFERROR(IF(VLOOKUP($A20,int_ai_sample!$A$2:$N$101,11,FALSE)=VLOOKUP($A20,人工標註!$A$2:$N$30,11,FALSE),"是","否"),"") -> 是 | M20: =IFERROR(IF(VLOOKUP($A20,int_ai_sample!$A$2:$N$101,12,FALSE)=VLOOKUP($A20,人工標註!$A$2:$N$30,12,FALSE),"是","否"),"") -> 是 | N20: =IFERROR(IF(VLOOKUP($A20,int_ai_sample!$A$2:$N$101,13,FALSE)=VLOOKUP($A20,人工標註!$A$2:$N$30,13,FALSE),"是","否"),"") -> 是 | O20: =IFERROR(IF(VLOOKUP($A20,int_ai_sample!$A$2:$N$101,14,FALSE)=VLOOKUP($A20,人工標註!$A$2:$N$30,14,FALSE),"是","否"),"") -> 是
A21: 2e68adb91fc0eb9ff9ef97c79dad5104 | B21: =IFERROR(VLOOKUP($A21,int_ai_sample!$A$2:$N$101,3,FALSE),"") -> 2 | C21: =IFERROR(VLOOKUP($A21,int_ai_sample!$A$2:$N$101,5,FALSE),"") -> 我沒有收到商品。 | D21: =IFERROR(VLOOKUP($A21,int_ai_sample!$A$2:$N$101,6,FALSE),"") -> negative | E21: =IFERROR(VLOOKUP($A21,人工標註!$A$2:$N$30,6,FALSE),"") -> negative | F21: =IF(OR(D21="",E21=""),"",IF(D21=E21,"是","否")) -> 是 | G21: =ROUND(COUNTIF($F$2:$F$30,"是")/30,2) -> 0.83 | H21: =IFERROR(IF(VLOOKUP($A21,int_ai_sample!$A$2:$N$101,7,FALSE)=VLOOKUP($A21,人工標註!$A$2:$N$30,7,FALSE),"是","否"),"") -> 是 | I21: =IFERROR(IF(VLOOKUP($A21,int_ai_sample!$A$2:$N$101,8,FALSE)=VLOOKUP($A21,人工標註!$A$2:$N$30,8,FALSE),"是","否"),"") -> 是 | J21: =IFERROR(IF(VLOOKUP($A21,int_ai_sample!$A$2:$N$101,9,FALSE)=VLOOKUP($A21,人工標註!$A$2:$N$30,9,FALSE),"是","否"),"") -> 是 | K21: =IFERROR(IF(VLOOKUP($A21,int_ai_sample!$A$2:$N$101,10,FALSE)=VLOOKUP($A21,人工標註!$A$2:$N$30,10,FALSE),"是","否"),"") -> 是 | L21: =IFERROR(IF(VLOOKUP($A21,int_ai_sample!$A$2:$N$101,11,FALSE)=VLOOKUP($A21,人工標註!$A$2:$N$30,11,FALSE),"是","否"),"") -> 是 | M21: =IFERROR(IF(VLOOKUP($A21,int_ai_sample!$A$2:$N$101,12,FALSE)=VLOOKUP($A21,人工標註!$A$2:$N$30,12,FALSE),"是","否"),"") -> 是 | N21: =IFERROR(IF(VLOOKUP($A21,int_ai_sample!$A$2:$N$101,13,FALSE)=VLOOKUP($A21,人工標註!$A$2:$N$30,13,FALSE),"是","否"),"") -> 是 | O21: =IFERROR(IF(VLOOKUP($A21,int_ai_sample!$A$2:$N$101,14,FALSE)=VLOOKUP($A21,人工標註!$A$2:$N$30,14,FALSE),"是","否"),"") -> 是
A22: 2e948224ec4bf8fab2b705e05a81da38 | B22: =IFERROR(VLOOKUP($A22,int_ai_sample!$A$2:$N$101,3,FALSE),"") -> 1 | C22: =IFERROR(VLOOKUP($A22,int_ai_sample!$A$2:$N$101,5,FALSE),"") -> 我申請了更換，對方說兩天內會回覆我，讓我把商品退回商店，但到現在都沒有回覆。我不要這個塑膠製品。 | D22: =IFERROR(VLOOKUP($A22,int_ai_sample!$A$2:$N$101,6,FALSE),"") -> negative | E22: =IFERROR(VLOOKUP($A22,人工標註!$A$2:$N$30,6,FALSE),"") -> negative | F22: =IF(OR(D22="",E22=""),"",IF(D22=E22,"是","否")) -> 是 | G22: =ROUND(COUNTIF($F$2:$F$30,"是")/30,2) -> 0.83 | H22: =IFERROR(IF(VLOOKUP($A22,int_ai_sample!$A$2:$N$101,7,FALSE)=VLOOKUP($A22,人工標註!$A$2:$N$30,7,FALSE),"是","否"),"") -> 是 | I22: =IFERROR(IF(VLOOKUP($A22,int_ai_sample!$A$2:$N$101,8,FALSE)=VLOOKUP($A22,人工標註!$A$2:$N$30,8,FALSE),"是","否"),"") -> 是 | J22: =IFERROR(IF(VLOOKUP($A22,int_ai_sample!$A$2:$N$101,9,FALSE)=VLOOKUP($A22,人工標註!$A$2:$N$30,9,FALSE),"是","否"),"") -> 否 | K22: =IFERROR(IF(VLOOKUP($A22,int_ai_sample!$A$2:$N$101,10,FALSE)=VLOOKUP($A22,人工標註!$A$2:$N$30,10,FALSE),"是","否"),"") -> 是 | L22: =IFERROR(IF(VLOOKUP($A22,int_ai_sample!$A$2:$N$101,11,FALSE)=VLOOKUP($A22,人工標註!$A$2:$N$30,11,FALSE),"是","否"),"") -> 是 | M22: =IFERROR(IF(VLOOKUP($A22,int_ai_sample!$A$2:$N$101,12,FALSE)=VLOOKUP($A22,人工標註!$A$2:$N$30,12,FALSE),"是","否"),"") -> 是 | N22: =IFERROR(IF(VLOOKUP($A22,int_ai_sample!$A$2:$N$101,13,FALSE)=VLOOKUP($A22,人工標註!$A$2:$N$30,13,FALSE),"是","否"),"") -> 是 | O22: =IFERROR(IF(VLOOKUP($A22,int_ai_sample!$A$2:$N$101,14,FALSE)=VLOOKUP($A22,人工標註!$A$2:$N$30,14,FALSE),"是","否"),"") -> 是
A23: 3463ea11426e5dc8338ae33518f58c29 | B23: =IFERROR(VLOOKUP($A23,int_ai_sample!$A$2:$N$101,3,FALSE),"") -> 2 | C23: =IFERROR(VLOOKUP($A23,int_ai_sample!$A$2:$N$101,5,FALSE),"") -> 商品正確送達，但我覺得配送時間實在太、太慢了。 | D23: =IFERROR(VLOOKUP($A23,int_ai_sample!$A$2:$N$101,6,FALSE),"") -> negative | E23: =IFERROR(VLOOKUP($A23,人工標註!$A$2:$N$30,6,FALSE),"") -> mixed | F23: =IF(OR(D23="",E23=""),"",IF(D23=E23,"是","否")) -> 否 | G23: =ROUND(COUNTIF($F$2:$F$30,"是")/30,2) -> 0.83 | H23: =IFERROR(IF(VLOOKUP($A23,int_ai_sample!$A$2:$N$101,7,FALSE)=VLOOKUP($A23,人工標註!$A$2:$N$30,7,FALSE),"是","否"),"") -> 是 | I23: =IFERROR(IF(VLOOKUP($A23,int_ai_sample!$A$2:$N$101,8,FALSE)=VLOOKUP($A23,人工標註!$A$2:$N$30,8,FALSE),"是","否"),"") -> 否 | J23: =IFERROR(IF(VLOOKUP($A23,int_ai_sample!$A$2:$N$101,9,FALSE)=VLOOKUP($A23,人工標註!$A$2:$N$30,9,FALSE),"是","否"),"") -> 是 | K23: =IFERROR(IF(VLOOKUP($A23,int_ai_sample!$A$2:$N$101,10,FALSE)=VLOOKUP($A23,人工標註!$A$2:$N$30,10,FALSE),"是","否"),"") -> 是 | L23: =IFERROR(IF(VLOOKUP($A23,int_ai_sample!$A$2:$N$101,11,FALSE)=VLOOKUP($A23,人工標註!$A$2:$N$30,11,FALSE),"是","否"),"") -> 是 | M23: =IFERROR(IF(VLOOKUP($A23,int_ai_sample!$A$2:$N$101,12,FALSE)=VLOOKUP($A23,人工標註!$A$2:$N$30,12,FALSE),"是","否"),"") -> 是 | N23: =IFERROR(IF(VLOOKUP($A23,int_ai_sample!$A$2:$N$101,13,FALSE)=VLOOKUP($A23,人工標註!$A$2:$N$30,13,FALSE),"是","否"),"") -> 是 | O23: =IFERROR(IF(VLOOKUP($A23,int_ai_sample!$A$2:$N$101,14,FALSE)=VLOOKUP($A23,人工標註!$A$2:$N$30,14,FALSE),"是","否"),"") -> 是
A24: 38b7052e458c9d2f5f4e620a52df56ae | B24: =IFERROR(VLOOKUP($A24,int_ai_sample!$A$2:$N$101,3,FALSE),"") -> 1 | C24: =IFERROR(VLOOKUP($A24,int_ai_sample!$A$2:$N$101,5,FALSE),"") -> 我無法取得商品配送的相關資訊。 | D24: =IFERROR(VLOOKUP($A24,int_ai_sample!$A$2:$N$101,6,FALSE),"") -> negative | E24: =IFERROR(VLOOKUP($A24,人工標註!$A$2:$N$30,6,FALSE),"") -> negative | F24: =IF(OR(D24="",E24=""),"",IF(D24=E24,"是","否")) -> 是 | G24: =ROUND(COUNTIF($F$2:$F$30,"是")/30,2) -> 0.83 | H24: =IFERROR(IF(VLOOKUP($A24,int_ai_sample!$A$2:$N$101,7,FALSE)=VLOOKUP($A24,人工標註!$A$2:$N$30,7,FALSE),"是","否"),"") -> 否 | I24: =IFERROR(IF(VLOOKUP($A24,int_ai_sample!$A$2:$N$101,8,FALSE)=VLOOKUP($A24,人工標註!$A$2:$N$30,8,FALSE),"是","否"),"") -> 是 | J24: =IFERROR(IF(VLOOKUP($A24,int_ai_sample!$A$2:$N$101,9,FALSE)=VLOOKUP($A24,人工標註!$A$2:$N$30,9,FALSE),"是","否"),"") -> 是 | K24: =IFERROR(IF(VLOOKUP($A24,int_ai_sample!$A$2:$N$101,10,FALSE)=VLOOKUP($A24,人工標註!$A$2:$N$30,10,FALSE),"是","否"),"") -> 是 | L24: =IFERROR(IF(VLOOKUP($A24,int_ai_sample!$A$2:$N$101,11,FALSE)=VLOOKUP($A24,人工標註!$A$2:$N$30,11,FALSE),"是","否"),"") -> 是 | M24: =IFERROR(IF(VLOOKUP($A24,int_ai_sample!$A$2:$N$101,12,FALSE)=VLOOKUP($A24,人工標註!$A$2:$N$30,12,FALSE),"是","否"),"") -> 是 | N24: =IFERROR(IF(VLOOKUP($A24,int_ai_sample!$A$2:$N$101,13,FALSE)=VLOOKUP($A24,人工標註!$A$2:$N$30,13,FALSE),"是","否"),"") -> 是 | O24: =IFERROR(IF(VLOOKUP($A24,int_ai_sample!$A$2:$N$101,14,FALSE)=VLOOKUP($A24,人工標註!$A$2:$N$30,14,FALSE),"是","否"),"") -> 是
A25: 3b414288c372edf633fc654aff5aa11f | B25: =IFERROR(VLOOKUP($A25,int_ai_sample!$A$2:$N$101,3,FALSE),"") -> 1 | C25: =IFERROR(VLOOKUP($A25,int_ai_sample!$A$2:$N$101,5,FALSE),"") -> 這個娃娃沒有符合我在 lannister 的攤位看到的規格/內容。 | D25: =IFERROR(VLOOKUP($A25,int_ai_sample!$A$2:$N$101,6,FALSE),"") -> negative | E25: =IFERROR(VLOOKUP($A25,人工標註!$A$2:$N$30,6,FALSE),"") -> negative | F25: =IF(OR(D25="",E25=""),"",IF(D25=E25,"是","否")) -> 是 | G25: =ROUND(COUNTIF($F$2:$F$30,"是")/30,2) -> 0.83 | H25: =IFERROR(IF(VLOOKUP($A25,int_ai_sample!$A$2:$N$101,7,FALSE)=VLOOKUP($A25,人工標註!$A$2:$N$30,7,FALSE),"是","否"),"") -> 是 | I25: =IFERROR(IF(VLOOKUP($A25,int_ai_sample!$A$2:$N$101,8,FALSE)=VLOOKUP($A25,人工標註!$A$2:$N$30,8,FALSE),"是","否"),"") -> 是 | J25: =IFERROR(IF(VLOOKUP($A25,int_ai_sample!$A$2:$N$101,9,FALSE)=VLOOKUP($A25,人工標註!$A$2:$N$30,9,FALSE),"是","否"),"") -> 是 | K25: =IFERROR(IF(VLOOKUP($A25,int_ai_sample!$A$2:$N$101,10,FALSE)=VLOOKUP($A25,人工標註!$A$2:$N$30,10,FALSE),"是","否"),"") -> 是 | L25: =IFERROR(IF(VLOOKUP($A25,int_ai_sample!$A$2:$N$101,11,FALSE)=VLOOKUP($A25,人工標註!$A$2:$N$30,11,FALSE),"是","否"),"") -> 是 | M25: =IFERROR(IF(VLOOKUP($A25,int_ai_sample!$A$2:$N$101,12,FALSE)=VLOOKUP($A25,人工標註!$A$2:$N$30,12,FALSE),"是","否"),"") -> 是 | N25: =IFERROR(IF(VLOOKUP($A25,int_ai_sample!$A$2:$N$101,13,FALSE)=VLOOKUP($A25,人工標註!$A$2:$N$30,13,FALSE),"是","否"),"") -> 是 | O25: =IFERROR(IF(VLOOKUP($A25,int_ai_sample!$A$2:$N$101,14,FALSE)=VLOOKUP($A25,人工標註!$A$2:$N$30,14,FALSE),"是","否"),"") -> 是
A26: 3b5f86cdad4d63df0a7f09296a1ebdbc | B26: =IFERROR(VLOOKUP($A26,int_ai_sample!$A$2:$N$101,3,FALSE),"") -> 3 | C26: =IFERROR(VLOOKUP($A26,int_ai_sample!$A$2:$N$101,5,FALSE),"") -> 我覺得交貨期不錯應該 15 天像其他店一樣，但跟你們買幾乎要一個月。 | D26: =IFERROR(VLOOKUP($A26,int_ai_sample!$A$2:$N$101,6,FALSE),"") -> negative | E26: =IFERROR(VLOOKUP($A26,人工標註!$A$2:$N$30,6,FALSE),"") -> mixed | F26: =IF(OR(D26="",E26=""),"",IF(D26=E26,"是","否")) -> 否 | G26: =ROUND(COUNTIF($F$2:$F$30,"是")/30,2) -> 0.83 | H26: =IFERROR(IF(VLOOKUP($A26,int_ai_sample!$A$2:$N$101,7,FALSE)=VLOOKUP($A26,人工標註!$A$2:$N$30,7,FALSE),"是","否"),"") -> 是 | I26: =IFERROR(IF(VLOOKUP($A26,int_ai_sample!$A$2:$N$101,8,FALSE)=VLOOKUP($A26,人工標註!$A$2:$N$30,8,FALSE),"是","否"),"") -> 是 | J26: =IFERROR(IF(VLOOKUP($A26,int_ai_sample!$A$2:$N$101,9,FALSE)=VLOOKUP($A26,人工標註!$A$2:$N$30,9,FALSE),"是","否"),"") -> 是 | K26: =IFERROR(IF(VLOOKUP($A26,int_ai_sample!$A$2:$N$101,10,FALSE)=VLOOKUP($A26,人工標註!$A$2:$N$30,10,FALSE),"是","否"),"") -> 是 | L26: =IFERROR(IF(VLOOKUP($A26,int_ai_sample!$A$2:$N$101,11,FALSE)=VLOOKUP($A26,人工標註!$A$2:$N$30,11,FALSE),"是","否"),"") -> 是 | M26: =IFERROR(IF(VLOOKUP($A26,int_ai_sample!$A$2:$N$101,12,FALSE)=VLOOKUP($A26,人工標註!$A$2:$N$30,12,FALSE),"是","否"),"") -> 是 | N26: =IFERROR(IF(VLOOKUP($A26,int_ai_sample!$A$2:$N$101,13,FALSE)=VLOOKUP($A26,人工標註!$A$2:$N$30,13,FALSE),"是","否"),"") -> 是 | O26: =IFERROR(IF(VLOOKUP($A26,int_ai_sample!$A$2:$N$101,14,FALSE)=VLOOKUP($A26,人工標註!$A$2:$N$30,14,FALSE),"是","否"),"") -> 是
A27: 3b62bf0d1593a5a1743a3ca3f3aad2f9 | B27: =IFERROR(VLOOKUP($A27,int_ai_sample!$A$2:$N$101,3,FALSE),"") -> 3 | C27: =IFERROR(VLOOKUP($A27,int_ai_sample!$A$2:$N$101,5,FALSE),"") -> 符合期待，但還沒安裝。 | D27: =IFERROR(VLOOKUP($A27,int_ai_sample!$A$2:$N$101,6,FALSE),"") -> neutral | E27: =IFERROR(VLOOKUP($A27,人工標註!$A$2:$N$30,6,FALSE),"") -> neutral | F27: =IF(OR(D27="",E27=""),"",IF(D27=E27,"是","否")) -> 是 | G27: =ROUND(COUNTIF($F$2:$F$30,"是")/30,2) -> 0.83 | H27: =IFERROR(IF(VLOOKUP($A27,int_ai_sample!$A$2:$N$101,7,FALSE)=VLOOKUP($A27,人工標註!$A$2:$N$30,7,FALSE),"是","否"),"") -> 是 | I27: =IFERROR(IF(VLOOKUP($A27,int_ai_sample!$A$2:$N$101,8,FALSE)=VLOOKUP($A27,人工標註!$A$2:$N$30,8,FALSE),"是","否"),"") -> 是 | J27: =IFERROR(IF(VLOOKUP($A27,int_ai_sample!$A$2:$N$101,9,FALSE)=VLOOKUP($A27,人工標註!$A$2:$N$30,9,FALSE),"是","否"),"") -> 是 | K27: =IFERROR(IF(VLOOKUP($A27,int_ai_sample!$A$2:$N$101,10,FALSE)=VLOOKUP($A27,人工標註!$A$2:$N$30,10,FALSE),"是","否"),"") -> 是 | L27: =IFERROR(IF(VLOOKUP($A27,int_ai_sample!$A$2:$N$101,11,FALSE)=VLOOKUP($A27,人工標註!$A$2:$N$30,11,FALSE),"是","否"),"") -> 是 | M27: =IFERROR(IF(VLOOKUP($A27,int_ai_sample!$A$2:$N$101,12,FALSE)=VLOOKUP($A27,人工標註!$A$2:$N$30,12,FALSE),"是","否"),"") -> 是 | N27: =IFERROR(IF(VLOOKUP($A27,int_ai_sample!$A$2:$N$101,13,FALSE)=VLOOKUP($A27,人工標註!$A$2:$N$30,13,FALSE),"是","否"),"") -> 是 | O27: =IFERROR(IF(VLOOKUP($A27,int_ai_sample!$A$2:$N$101,14,FALSE)=VLOOKUP($A27,人工標註!$A$2:$N$30,14,FALSE),"是","否"),"") -> 是
A28: 3b84059929769dce04b06199d49e9999 | B28: =IFERROR(VLOOKUP($A28,int_ai_sample!$A$2:$N$101,3,FALSE),"") -> 2 | C28: =IFERROR(VLOOKUP($A28,int_ai_sample!$A$2:$N$101,5,FALSE),"") -> 商品預計在 11/11/2017 送達，但到現在都還沒有；訂單狀態是「配送有困難，商品尚未到達目的地」。如果週二14/11之前收不到，我就會採取行動。 | D28: =IFERROR(VLOOKUP($A28,int_ai_sample!$A$2:$N$101,6,FALSE),"") -> negative | E28: =IFERROR(VLOOKUP($A28,人工標註!$A$2:$N$30,6,FALSE),"") -> neutral | F28: =IF(OR(D28="",E28=""),"",IF(D28=E28,"是","否")) -> 否 | G28: =ROUND(COUNTIF($F$2:$F$30,"是")/30,2) -> 0.83 | H28: =IFERROR(IF(VLOOKUP($A28,int_ai_sample!$A$2:$N$101,7,FALSE)=VLOOKUP($A28,人工標註!$A$2:$N$30,7,FALSE),"是","否"),"") -> 是 | I28: =IFERROR(IF(VLOOKUP($A28,int_ai_sample!$A$2:$N$101,8,FALSE)=VLOOKUP($A28,人工標註!$A$2:$N$30,8,FALSE),"是","否"),"") -> 是 | J28: =IFERROR(IF(VLOOKUP($A28,int_ai_sample!$A$2:$N$101,9,FALSE)=VLOOKUP($A28,人工標註!$A$2:$N$30,9,FALSE),"是","否"),"") -> 是 | K28: =IFERROR(IF(VLOOKUP($A28,int_ai_sample!$A$2:$N$101,10,FALSE)=VLOOKUP($A28,人工標註!$A$2:$N$30,10,FALSE),"是","否"),"") -> 是 | L28: =IFERROR(IF(VLOOKUP($A28,int_ai_sample!$A$2:$N$101,11,FALSE)=VLOOKUP($A28,人工標註!$A$2:$N$30,11,FALSE),"是","否"),"") -> 是 | M28: =IFERROR(IF(VLOOKUP($A28,int_ai_sample!$A$2:$N$101,12,FALSE)=VLOOKUP($A28,人工標註!$A$2:$N$30,12,FALSE),"是","否"),"") -> 是 | N28: =IFERROR(IF(VLOOKUP($A28,int_ai_sample!$A$2:$N$101,13,FALSE)=VLOOKUP($A28,人工標註!$A$2:$N$30,13,FALSE),"是","否"),"") -> 是 | O28: =IFERROR(IF(VLOOKUP($A28,int_ai_sample!$A$2:$N$101,14,FALSE)=VLOOKUP($A28,人工標註!$A$2:$N$30,14,FALSE),"是","否"),"") -> 是
... A30: 467429497f2711eb1e33e710897e04a8 | B30: =IFERROR(VLOOKUP($A30,int_ai_sample!$A$2:$N$101,3,FALSE),"") -> 4 | C30: =IFERROR(VLOOKUP($A30,int_ai_sample!$A$2:$N$101,5,FALSE),"") -> 不錯的產品，我喜歡！也恭喜你們店家，提前交貨！我推薦。 | D30: =IFERROR(VLOOKUP($A30,int_ai_sample!$A$2:$N$101,6,FALSE),"") -> positive | E30: =IFERROR(VLOOKUP($A30,人工標註!$A$2:$N$30,6,FALSE),"") -> positive | F30: =IF(OR(D30="",E30=""),"",IF(D30=E30,"是","否")) -> 是 | G30: =ROUND(COUNTIF($F$2:$F$30,"是")/30,2) -> 0.83 | H30: =IFERROR(IF(VLOOKUP($A30,int_ai_sample!$A$2:$N$101,7,FALSE)=VLOOKUP($A30,人工標註!$A$2:$N$30,7,FALSE),"是","否"),"") -> 是 | I30: =IFERROR(IF(VLOOKUP($A30,int_ai_sample!$A$2:$N$101,8,FALSE)=VLOOKUP($A30,人工標註!$A$2:$N$30,8,FALSE),"是","否"),"") -> 是 | J30: =IFERROR(IF(VLOOKUP($A30,int_ai_sample!$A$2:$N$101,9,FALSE)=VLOOKUP($A30,人工標註!$A$2:$N$30,9,FALSE),"是","否"),"") -> 是 | K30: =IFERROR(IF(VLOOKUP($A30,int_ai_sample!$A$2:$N$101,10,FALSE)=VLOOKUP($A30,人工標註!$A$2:$N$30,10,FALSE),"是","否"),"") -> 是 | L30: =IFERROR(IF(VLOOKUP($A30,int_ai_sample!$A$2:$N$101,11,FALSE)=VLOOKUP($A30,人工標註!$A$2:$N$30,11,FALSE),"是","否"),"") -> 是 | M30: =IFERROR(IF(VLOOKUP($A30,int_ai_sample!$A$2:$N$101,12,FALSE)=VLOOKUP($A30,人工標註!$A$2:$N$30,12,FALSE),"是","否"),"") -> 是 | N30: =IFERROR(IF(VLOOKUP($A30,int_ai_sample!$A$2:$N$101,13,FALSE)=VLOOKUP($A30,人工標註!$A$2:$N$30,13,FALSE),"是","否"),"") -> 是 | O30: =IFERROR(IF(VLOOKUP($A30,int_ai_sample!$A$2:$N$101,14,FALSE)=VLOOKUP($A30,人工標註!$A$2:$N$30,14,FALSE),"是","否"),"") -> 是
