Workbook

Sheet int_ai_sample_v2
A1: review_id | B1: order_id | C1: review_score | D1: review_comment_title_message | E1: review_translation_tw | F1: sentiment | G1: t01_delivery_logistics | H1: t02_order_fulfillment | I1: t03_product_quality | J1: t04_product_consistency | K1: t05_packaging_protection | L1: t06_customer_service | M1: t07_price_transaction | N1: t08_platform_system
A2: 02756b804af267483fa850049b9e27ec | B2: 10c3c7fea20a1ed15c6e55e90b3fb084 | C2: 1 | D2: Não recebi o produto e nem meu dinheiro de volta | E2: 我沒有收到商品，也沒有退回我的錢。 | F2: negative | G2: 1 | H2: 0 | I2: 0 | J2: 0 | K2: 0 | L2: 0 | M2: 1 | N2: 0
A3: 037d5c42ae0be99806581248e36789b0 | B3: b78e1e59e42553fbbc9948d04ef0539f | C3: 4 | D3: Produto entregue antes do prazo limite, de fácil rastreabilidade e embalagens adequadas. | E3: 在交期內提早送達，方便追蹤物流，而且包裝也合適。 | F3: positive | G3: 1 | H3: 0 | I3: 0 | J3: 0 | K3: 1 | L3: 0 | M3: 0 | N3: 0
A4: 03e9be6f310adce47bb7b3ba836482f9 | B4: 4516c79ac42f6a567bf4d1209eba2b33 | C4: 3 | D4: Na imagem parece ser uma lâmpada maior e na verdade é a menor e na descrição não vem informando qual tipo de lâmpada. | E4: 圖片看起來像更大的燈，結果其實是最小的；而且描述裡沒有說明是哪一種燈泡。 | F4: negative | G4: 0 | H4: 0 | I4: 0 | J4: 1 | K4: 0 | L4: 0 | M4: 0 | N4: 0
A5: 05dad1a1157fbb3d160559720871c42b | B5: 17f7971d77f3b781ed3a2846c5d41946 | C5: 4 | D5: bom produto conforme mostrado no site | E5: 好商品，符合網站上展示的內容。 | F5: positive | G5: 0 | H5: 0 | I5: 0 | J5: 1 | K5: 0 | L5: 0 | M5: 0 | N5: 0
A6: 05f095f88fbec384ffda29a9c8145ca0 | B6: da28ac567f1bbe704eb39c1d21c53a0d | C6: 4 | D6: Suporte é bem prático e resistente. | E6: 支援/支架很好用，也很耐用。 | F6: positive | G6: 0 | H6: 0 | I6: 1 | J6: 0 | K6: 0 | L6: 0 | M6: 0 | N6: 0
A7: 0eb8fd67c98a9b0e14316f4396e86b57 | B7: 528588e5accc2b1c808576e68fd1d46c | C7: 2 | D7: Fiz a compra e meu pedido não chegou e dar como entregue!!! | E7: 我下單了，但我的包裹沒有到，卻顯示已送達！ | F7: negative | G7: 1 | H7: 0 | I7: 0 | J7: 0 | K7: 0 | L7: 0 | M7: 0 | N7: 0
A8: 0f34e9cbc1e263a35f942a0c92a20162 | B8: 856f18ac2d008bc9a92673a46c6057ce | C8: 2 | D8: Produto entregue parcialmente, só chegou uma luminária a de cor preta, a outra luminária não foi enviada até o presente momento. | E8: 商品是分批送達的，但只收到一盞黑色的檯燈；另一盞檯燈到現在還沒寄來。 | F8: negative | G8: 1 | H8: 1 | I8: 0 | J8: 0 | K8: 0 | L8: 0 | M8: 0 | N8: 0
A9: 0f8e2790c6eb33609495046bd6b5e9f2 | B9: 7edf24d26573e36b72c670b3810ab3e0 | C9: 1 | D9: Comprei um relógio Oakley Minute Machine e chegou relógio falsificado da pior qualidade e com a nota fiscal em nome de outra pessoa. Vou entrar na justiça contra vocês. | E9: 我買的是 Oakley Minute Machine 的手錶，但收到的是假貨，品質最差，而且發票開在另一個人的名下。我會對你們提告。 | F9: negative | G9: 0 | H9: 0 | I9: 1 | J9: 1 | K9: 0 | L9: 0 | M9: 0 | N9: 0
A10: 154876b5dee18a5391c7f3813cb64618 | B10: b9112da66c99f7f73aed69802cb358f7 | C10: 4 | D10: Cartucho aparenta ser bom, vamos ver com o uso. | E10: 這個墨盒看起來不錯，之後用看看。 | F10: neutral | G10: 0 | H10: 0 | I10: 1 | J10: 0 | K10: 0 | L10: 0 | M10: 0 | N10: 0
A11: 170f333c55189a2433e4bd944cae3eb2 | B11: df82ea7ca7f0f799161e0fd92c3ab96a | C11: 3 | D11: A avaliação geral foi regular porque ainda não testei o produto. Avaliei a compra/entrega. | E11: 整體評價一般，因為我還沒測試產品。我是評估購買/交付。 | F11: neutral | G11: 0 | H11: 0 | I11: 0 | J11: 0 | K11: 0 | L11: 0 | M11: 0 | N11: 0
A12: 190f5817bf369b18149d2fd6fea8ed5c | B12: d072b2eadd483cbf8b54f0ff76ef879d | C12: 1 | D12: não recebi ainda! | E12: 我還沒收到！ | F12: negative | G12: 1 | H12: 0 | I12: 0 | J12: 0 | K12: 0 | L12: 0 | M12: 0 | N12: 0
A13: 1937557c43952cfaafa9474b8a0a0f2d | B13: 20824f4d96365315a1f191746a385a0c | C13: 5 | D13: super recomendo Parabéns pela respeito ao consumidor ! | E13: 我超級推薦！也祝賀你們對消費者的尊重！ | F13: positive | G13: 0 | H13: 0 | I13: 0 | J13: 0 | K13: 0 | L13: 1 | M13: 0 | N13: 0
... A101: fcaf726c0b61b07ef40c8bc2a3e9eeb2 | B101: 83497c05dd75dfe740fb8b0c5482da3b | C101: 4 | D101: Outras vezes foi tudo ok dessa não sei que ouve | E101: 其他次都一切OK，這次不知道發生了什麼。 | F101: neutral | G101: 0 | H101: 0 | I101: 0 | J101: 0 | K101: 0 | L101: 0 | M101: 0 | N101: 0

Sheet 人工標注
A1: review_id | B1: order_id | C1: review_score | D1: review_comment_title_message | E1: review_translation_tw | F1: sentiment人工標注 | G1: t01_delivery_logistics | H1: t02_order_fulfillment | I1: t03_product_quality | J1: t04_product_consistency | K1: t05_packaging_protection | L1: t06_customer_service | M1: t07_price_transaction | N1: t08_platform_system
A2: 02756b804af267483fa850049b9e27ec | B2: 10c3c7fea20a1ed15c6e55e90b3fb084 | C2: 1 | D2: Não recebi o produto e nem meu dinheiro de volta | E2: 我沒有收到商品，也沒有退回我的錢。 | F2: negative | G2: 1 | H2: 0 | I2: 0 | J2: 0 | K2: 0 | L2: 0 | M2: 1 | N2: 0
A3: 037d5c42ae0be99806581248e36789b0 | B3: b78e1e59e42553fbbc9948d04ef0539f | C3: 4 | D3: Produto entregue antes do prazo limite, de fácil rastreabilidade e embalagens adequadas. | E3: 在交期內提早送達，方便追蹤物流，而且包裝也合適。 | F3: positive | G3: 1 | H3: 0 | I3: 0 | J3: 0 | K3: 1 | L3: 0 | M3: 0 | N3: 0
A4: 03e9be6f310adce47bb7b3ba836482f9 | B4: 4516c79ac42f6a567bf4d1209eba2b33 | C4: 3 | D4: Na imagem parece ser uma lâmpada maior e na verdade é a menor e na descrição não vem informando qual tipo de lâmpada. | E4: 圖片看起來像更大的燈，結果其實是最小的；而且描述裡沒有說明是哪一種燈泡。 | F4: negative | G4: 0 | H4: 0 | I4: 0 | J4: 1 | K4: 0 | L4: 0 | M4: 0 | N4: 0
A5: 05dad1a1157fbb3d160559720871c42b | B5: 17f7971d77f3b781ed3a2846c5d41946 | C5: 4 | D5: bom produto conforme mostrado no site | E5: 好商品，符合網站上展示的內容。 | F5: positive | G5: 0 | H5: 0 | I5: 1 | J5: 1 | K5: 0 | L5: 0 | M5: 0 | N5: 0
A6: 05f095f88fbec384ffda29a9c8145ca0 | B6: da28ac567f1bbe704eb39c1d21c53a0d | C6: 4 | D6: Suporte é bem prático e resistente. | E6: 支援/支架很好用，也很耐用。 | F6: positive | G6: 0 | H6: 0 | I6: 0 | J6: 0 | K6: 0 | L6: 0 | M6: 0 | N6: 0
A7: 0eb8fd67c98a9b0e14316f4396e86b57 | B7: 528588e5accc2b1c808576e68fd1d46c | C7: 2 | D7: Fiz a compra e meu pedido não chegou e dar como entregue!!! | E7: 我下單了，但我的包裹沒有到，卻顯示已送達！ | F7: negative | G7: 1 | H7: 0 | I7: 0 | J7: 0 | K7: 0 | L7: 0 | M7: 0 | N7: 0
A8: 0f34e9cbc1e263a35f942a0c92a20162 | B8: 856f18ac2d008bc9a92673a46c6057ce | C8: 2 | D8: Produto entregue parcialmente, só chegou uma luminária a de cor preta, a outra luminária não foi enviada até o presente momento. | E8: 商品是分批送達的，但只收到一盞黑色的檯燈；另一盞檯燈到現在還沒寄來。 | F8: negative | G8: 1 | H8: 1 | I8: 0 | J8: 0 | K8: 0 | L8: 0 | M8: 0 | N8: 0
A9: 0f8e2790c6eb33609495046bd6b5e9f2 | B9: 7edf24d26573e36b72c670b3810ab3e0 | C9: 1 | D9: Comprei um relógio Oakley Minute Machine e chegou relógio falsificado da pior qualidade e com a nota fiscal em nome de outra pessoa. Vou entrar na justiça contra vocês. | E9: 我買的是 Oakley Minute Machine 的手錶，但收到的是假貨，品質最差，而且發票開在另一個人的名下。我會對你們提告。 | F9: negative | G9: 0 | H9: 0 | I9: 1 | J9: 0 | K9: 0 | L9: 0 | M9: 0 | N9: 1
A10: 154876b5dee18a5391c7f3813cb64618 | B10: b9112da66c99f7f73aed69802cb358f7 | C10: 4 | D10: Cartucho aparenta ser bom, vamos ver com o uso. | E10: 這個墨盒看起來不錯，之後用看看。 | F10: positive | G10: 0 | H10: 0 | I10: 1 | J10: 0 | K10: 0 | L10: 0 | M10: 0 | N10: 0
A11: 170f333c55189a2433e4bd944cae3eb2 | B11: df82ea7ca7f0f799161e0fd92c3ab96a | C11: 3 | D11: A avaliação geral foi regular porque ainda não testei o produto. Avaliei a compra/entrega. | E11: 整體評價一般，因為我還沒測試產品。我是評估購買/交付。 | F11: neutral | G11: 0 | H11: 0 | I11: 0 | J11: 0 | K11: 0 | L11: 0 | M11: 0 | N11: 0
A12: 190f5817bf369b18149d2fd6fea8ed5c | B12: d072b2eadd483cbf8b54f0ff76ef879d | C12: 1 | D12: não recebi ainda! | E12: 我還沒收到！ | F12: negative | G12: 1 | H12: 0 | I12: 0 | J12: 0 | K12: 0 | L12: 0 | M12: 0 | N12: 0
A13: 1937557c43952cfaafa9474b8a0a0f2d | B13: 20824f4d96365315a1f191746a385a0c | C13: 5 | D13: super recomendo Parabéns pela respeito ao consumidor ! | E13: 我超級推薦！也祝賀你們對消費者的尊重！ | F13: positive | G13: 0 | H13: 0 | I13: 0 | J13: 0 | K13: 0 | L13: 0 | M13: 0 | N13: 0
... A101: fcaf726c0b61b07ef40c8bc2a3e9eeb2 | B101: 83497c05dd75dfe740fb8b0c5482da3b | C101: 4 | D101: Outras vezes foi tudo ok dessa não sei que ouve | E101: 其他次都一切OK，這次不知道發生了什麼。 | F101: negative | G101: 0 | H101: 0 | I101: 0 | J101: 0 | K101: 0 | L101: 0 | M101: 0 | N101: 0

Sheet AI標注KPI
A1: review_id | B1: review_score | C1: review_translation_tw | D1: sentiment_AI | E1: sentiment_人工 | F1: Sentiment是否正確 | G1: Sentiment Accuracy(%) | H1: T01是否正確 | I1: T02是否正確 | J1: T03是否正確 | K1: T04是否正確 | L1: T05是否正確 | M1: T06是否正確 | N1: T07是否正確 | O1: T08是否正確 | R1: AI 標注驗證 KPI
A2: 02756b804af267483fa850049b9e27ec | B2: 1 | C2: 我沒有收到商品，也沒有退回我的錢。 | D2: =int_ai_sample_v2!F2 -> negative | E2: =人工標注!F2 -> negative | F2: =IF(D2=E2,"是","否") -> 是 | G2: =COUNTIF($F$2:$F$101,"是")/COUNTA($A$2:$A$101) -> 0.87 | H2: =IF(int_ai_sample_v2!G2=人工標注!G2,"是","否") -> 是 | I2: =IF(int_ai_sample_v2!H2=人工標注!H2,"是","否") -> 是 | J2: =IF(int_ai_sample_v2!I2=人工標注!I2,"是","否") -> 是 | K2: =IF(int_ai_sample_v2!J2=人工標注!J2,"是","否") -> 是 | L2: =IF(int_ai_sample_v2!K2=人工標注!K2,"是","否") -> 是 | M2: =IF(int_ai_sample_v2!L2=人工標注!L2,"是","否") -> 是 | N2: =IF(int_ai_sample_v2!M2=人工標注!M2,"是","否") -> 是 | O2: =IF(int_ai_sample_v2!N2=人工標注!N2,"是","否") -> 是 | R2: 有效樣本數 | S2: =COUNTA($A$2:$A$101) -> 100
A3: 037d5c42ae0be99806581248e36789b0 | B3: 4 | C3: 在交期內提早送達，方便追蹤物流，而且包裝也合適。 | D3: =int_ai_sample_v2!F3 -> positive | E3: =人工標注!F3 -> positive | F3: =IF(D3=E3,"是","否") -> 是 | G3: =COUNTIF($F$2:$F$101,"是")/COUNTA($A$2:$A$101) -> 0.87 | H3: =IF(int_ai_sample_v2!G3=人工標注!G3,"是","否") -> 是 | I3: =IF(int_ai_sample_v2!H3=人工標注!H3,"是","否") -> 是 | J3: =IF(int_ai_sample_v2!I3=人工標注!I3,"是","否") -> 是 | K3: =IF(int_ai_sample_v2!J3=人工標注!J3,"是","否") -> 是 | L3: =IF(int_ai_sample_v2!K3=人工標注!K3,"是","否") -> 是 | M3: =IF(int_ai_sample_v2!L3=人工標注!L3,"是","否") -> 是 | N3: =IF(int_ai_sample_v2!M3=人工標注!M3,"是","否") -> 是 | O3: =IF(int_ai_sample_v2!N3=人工標注!N3,"是","否") -> 是 | R3: Sentiment Accuracy | S3: =COUNTIF($F$2:$F$101,"是")/$S$2 -> 0.87
A4: 03e9be6f310adce47bb7b3ba836482f9 | B4: 3 | C4: 圖片看起來像更大的燈，結果其實是最小的；而且描述裡沒有說明是哪一種燈泡。 | D4: =int_ai_sample_v2!F4 -> negative | E4: =人工標注!F4 -> negative | F4: =IF(D4=E4,"是","否") -> 是 | G4: =COUNTIF($F$2:$F$101,"是")/COUNTA($A$2:$A$101) -> 0.87 | H4: =IF(int_ai_sample_v2!G4=人工標注!G4,"是","否") -> 是 | I4: =IF(int_ai_sample_v2!H4=人工標注!H4,"是","否") -> 是 | J4: =IF(int_ai_sample_v2!I4=人工標注!I4,"是","否") -> 是 | K4: =IF(int_ai_sample_v2!J4=人工標注!J4,"是","否") -> 是 | L4: =IF(int_ai_sample_v2!K4=人工標注!K4,"是","否") -> 是 | M4: =IF(int_ai_sample_v2!L4=人工標注!L4,"是","否") -> 是 | N4: =IF(int_ai_sample_v2!M4=人工標注!M4,"是","否") -> 是 | O4: =IF(int_ai_sample_v2!N4=人工標注!N4,"是","否") -> 是
A5: 05dad1a1157fbb3d160559720871c42b | B5: 4 | C5: 好商品，符合網站上展示的內容。 | D5: =int_ai_sample_v2!F5 -> positive | E5: =人工標注!F5 -> positive | F5: =IF(D5=E5,"是","否") -> 是 | G5: =COUNTIF($F$2:$F$101,"是")/COUNTA($A$2:$A$101) -> 0.87 | H5: =IF(int_ai_sample_v2!G5=人工標注!G5,"是","否") -> 是 | I5: =IF(int_ai_sample_v2!H5=人工標注!H5,"是","否") -> 是 | J5: =IF(int_ai_sample_v2!I5=人工標注!I5,"是","否") -> 否 | K5: =IF(int_ai_sample_v2!J5=人工標注!J5,"是","否") -> 是 | L5: =IF(int_ai_sample_v2!K5=人工標注!K5,"是","否") -> 是 | M5: =IF(int_ai_sample_v2!L5=人工標注!L5,"是","否") -> 是 | N5: =IF(int_ai_sample_v2!M5=人工標注!M5,"是","否") -> 是 | O5: =IF(int_ai_sample_v2!N5=人工標注!N5,"是","否") -> 是 | R5: Topic | S5: TP | T5: FP | U5: FN | V5: TN | W5: Precision | X5: Recall | Y5: F1 | Z5: Support
A6: 05f095f88fbec384ffda29a9c8145ca0 | B6: 4 | C6: 支援/支架很好用，也很耐用。 | D6: =int_ai_sample_v2!F6 -> positive | E6: =人工標注!F6 -> positive | F6: =IF(D6=E6,"是","否") -> 是 | G6: =COUNTIF($F$2:$F$101,"是")/COUNTA($A$2:$A$101) -> 0.87 | H6: =IF(int_ai_sample_v2!G6=人工標注!G6,"是","否") -> 是 | I6: =IF(int_ai_sample_v2!H6=人工標注!H6,"是","否") -> 是 | J6: =IF(int_ai_sample_v2!I6=人工標注!I6,"是","否") -> 否 | K6: =IF(int_ai_sample_v2!J6=人工標注!J6,"是","否") -> 是 | L6: =IF(int_ai_sample_v2!K6=人工標注!K6,"是","否") -> 是 | M6: =IF(int_ai_sample_v2!L6=人工標注!L6,"是","否") -> 是 | N6: =IF(int_ai_sample_v2!M6=人工標注!M6,"是","否") -> 是 | O6: =IF(int_ai_sample_v2!N6=人工標注!N6,"是","否") -> 是 | R6: T01 | S6: =COUNTIFS(int_ai_sample_v2!$G$2:$G$101,1,人工標注!$G$2:$G$101,1) -> 44 | T6: =COUNTIFS(int_ai_sample_v2!$G$2:$G$101,1,人工標注!$G$2:$G$101,0) -> 0 | U6: =COUNTIFS(int_ai_sample_v2!$G$2:$G$101,0,人工標注!$G$2:$G$101,1) -> 2 | V6: =COUNTIFS(int_ai_sample_v2!$G$2:$G$101,0,人工標注!$G$2:$G$101,0) -> 54 | W6: =IF(S6+T6=0,0,S6/(S6+T6)) -> 1 | X6: =IF(S6+U6=0,0,S6/(S6+U6)) -> 0.95652174 | Y6: =IF(W6+X6=0,0,2*W6*X6/(W6+X6)) -> 0.97777778 | Z6: =S6+U6 -> 46
A7: 0eb8fd67c98a9b0e14316f4396e86b57 | B7: 2 | C7: 我下單了，但我的包裹沒有到，卻顯示已送達！ | D7: =int_ai_sample_v2!F7 -> negative | E7: =人工標注!F7 -> negative | F7: =IF(D7=E7,"是","否") -> 是 | G7: =COUNTIF($F$2:$F$101,"是")/COUNTA($A$2:$A$101) -> 0.87 | H7: =IF(int_ai_sample_v2!G7=人工標注!G7,"是","否") -> 是 | I7: =IF(int_ai_sample_v2!H7=人工標注!H7,"是","否") -> 是 | J7: =IF(int_ai_sample_v2!I7=人工標注!I7,"是","否") -> 是 | K7: =IF(int_ai_sample_v2!J7=人工標注!J7,"是","否") -> 是 | L7: =IF(int_ai_sample_v2!K7=人工標注!K7,"是","否") -> 是 | M7: =IF(int_ai_sample_v2!L7=人工標注!L7,"是","否") -> 是 | N7: =IF(int_ai_sample_v2!M7=人工標注!M7,"是","否") -> 是 | O7: =IF(int_ai_sample_v2!N7=人工標注!N7,"是","否") -> 是 | R7: T02 | S7: =COUNTIFS(int_ai_sample_v2!$H$2:$H$101,1,人工標注!$H$2:$H$101,1) -> 11 | T7: =COUNTIFS(int_ai_sample_v2!$H$2:$H$101,1,人工標注!$H$2:$H$101,0) -> 3 | U7: =COUNTIFS(int_ai_sample_v2!$H$2:$H$101,0,人工標注!$H$2:$H$101,1) -> 6 | V7: =COUNTIFS(int_ai_sample_v2!$H$2:$H$101,0,人工標注!$H$2:$H$101,0) -> 80 | W7: =IF(S7+T7=0,0,S7/(S7+T7)) -> 0.78571429 | X7: =IF(S7+U7=0,0,S7/(S7+U7)) -> 0.64705882 | Y7: =IF(W7+X7=0,0,2*W7*X7/(W7+X7)) -> 0.70967742 | Z7: =S7+U7 -> 17
A8: 0f34e9cbc1e263a35f942a0c92a20162 | B8: 2 | C8: 商品是分批送達的，但只收到一盞黑色的檯燈；另一盞檯燈到現在還沒寄來。 | D8: =int_ai_sample_v2!F8 -> negative | E8: =人工標注!F8 -> negative | F8: =IF(D8=E8,"是","否") -> 是 | G8: =COUNTIF($F$2:$F$101,"是")/COUNTA($A$2:$A$101) -> 0.87 | H8: =IF(int_ai_sample_v2!G8=人工標注!G8,"是","否") -> 是 | I8: =IF(int_ai_sample_v2!H8=人工標注!H8,"是","否") -> 是 | J8: =IF(int_ai_sample_v2!I8=人工標注!I8,"是","否") -> 是 | K8: =IF(int_ai_sample_v2!J8=人工標注!J8,"是","否") -> 是 | L8: =IF(int_ai_sample_v2!K8=人工標注!K8,"是","否") -> 是 | M8: =IF(int_ai_sample_v2!L8=人工標注!L8,"是","否") -> 是 | N8: =IF(int_ai_sample_v2!M8=人工標注!M8,"是","否") -> 是 | O8: =IF(int_ai_sample_v2!N8=人工標注!N8,"是","否") -> 是 | R8: T03 | S8: =COUNTIFS(int_ai_sample_v2!$I$2:$I$101,1,人工標注!$I$2:$I$101,1) -> 15 | T8: =COUNTIFS(int_ai_sample_v2!$I$2:$I$101,1,人工標注!$I$2:$I$101,0) -> 4 | U8: =COUNTIFS(int_ai_sample_v2!$I$2:$I$101,0,人工標注!$I$2:$I$101,1) -> 3 | V8: =COUNTIFS(int_ai_sample_v2!$I$2:$I$101,0,人工標注!$I$2:$I$101,0) -> 78 | W8: =IF(S8+T8=0,0,S8/(S8+T8)) -> 0.78947368 | X8: =IF(S8+U8=0,0,S8/(S8+U8)) -> 0.83333333 | Y8: =IF(W8+X8=0,0,2*W8*X8/(W8+X8)) -> 0.81081081 | Z8: =S8+U8 -> 18
A9: 0f8e2790c6eb33609495046bd6b5e9f2 | B9: 1 | C9: 我買的是 Oakley Minute Machine 的手錶，但收到的是假貨，品質最差，而且發票開在另一個人的名下。我會對你們提告。 | D9: =int_ai_sample_v2!F9 -> negative | E9: =人工標注!F9 -> negative | F9: =IF(D9=E9,"是","否") -> 是 | G9: =COUNTIF($F$2:$F$101,"是")/COUNTA($A$2:$A$101) -> 0.87 | H9: =IF(int_ai_sample_v2!G9=人工標注!G9,"是","否") -> 是 | I9: =IF(int_ai_sample_v2!H9=人工標注!H9,"是","否") -> 是 | J9: =IF(int_ai_sample_v2!I9=人工標注!I9,"是","否") -> 是 | K9: =IF(int_ai_sample_v2!J9=人工標注!J9,"是","否") -> 否 | L9: =IF(int_ai_sample_v2!K9=人工標注!K9,"是","否") -> 是 | M9: =IF(int_ai_sample_v2!L9=人工標注!L9,"是","否") -> 是 | N9: =IF(int_ai_sample_v2!M9=人工標注!M9,"是","否") -> 是 | O9: =IF(int_ai_sample_v2!N9=人工標注!N9,"是","否") -> 否 | R9: T04 | S9: =COUNTIFS(int_ai_sample_v2!$J$2:$J$101,1,人工標注!$J$2:$J$101,1) -> 4 | T9: =COUNTIFS(int_ai_sample_v2!$J$2:$J$101,1,人工標注!$J$2:$J$101,0) -> 12 | U9: =COUNTIFS(int_ai_sample_v2!$J$2:$J$101,0,人工標注!$J$2:$J$101,1) -> 1 | V9: =COUNTIFS(int_ai_sample_v2!$J$2:$J$101,0,人工標注!$J$2:$J$101,0) -> 83 | W9: =IF(S9+T9=0,0,S9/(S9+T9)) -> 0.25 | X9: =IF(S9+U9=0,0,S9/(S9+U9)) -> 0.8 | Y9: =IF(W9+X9=0,0,2*W9*X9/(W9+X9)) -> 0.38095238 | Z9: =S9+U9 -> 5
A10: 154876b5dee18a5391c7f3813cb64618 | B10: 4 | C10: 這個墨盒看起來不錯，之後用看看。 | D10: =int_ai_sample_v2!F10 -> neutral | E10: =人工標注!F10 -> positive | F10: =IF(D10=E10,"是","否") -> 否 | G10: =COUNTIF($F$2:$F$101,"是")/COUNTA($A$2:$A$101) -> 0.87 | H10: =IF(int_ai_sample_v2!G10=人工標注!G10,"是","否") -> 是 | I10: =IF(int_ai_sample_v2!H10=人工標注!H10,"是","否") -> 是 | J10: =IF(int_ai_sample_v2!I10=人工標注!I10,"是","否") -> 是 | K10: =IF(int_ai_sample_v2!J10=人工標注!J10,"是","否") -> 是 | L10: =IF(int_ai_sample_v2!K10=人工標注!K10,"是","否") -> 是 | M10: =IF(int_ai_sample_v2!L10=人工標注!L10,"是","否") -> 是 | N10: =IF(int_ai_sample_v2!M10=人工標注!M10,"是","否") -> 是 | O10: =IF(int_ai_sample_v2!N10=人工標注!N10,"是","否") -> 是 | R10: T05 | S10: =COUNTIFS(int_ai_sample_v2!$K$2:$K$101,1,人工標注!$K$2:$K$101,1) -> 2 | T10: =COUNTIFS(int_ai_sample_v2!$K$2:$K$101,1,人工標注!$K$2:$K$101,0) -> 0 | U10: =COUNTIFS(int_ai_sample_v2!$K$2:$K$101,0,人工標注!$K$2:$K$101,1) -> 1 | V10: =COUNTIFS(int_ai_sample_v2!$K$2:$K$101,0,人工標注!$K$2:$K$101,0) -> 97 | W10: =IF(S10+T10=0,0,S10/(S10+T10)) -> 1 | X10: =IF(S10+U10=0,0,S10/(S10+U10)) -> 0.66666667 | Y10: =IF(W10+X10=0,0,2*W10*X10/(W10+X10)) -> 0.8 | Z10: =S10+U10 -> 3
A11: 170f333c55189a2433e4bd944cae3eb2 | B11: 3 | C11: 整體評價一般，因為我還沒測試產品。我是評估購買/交付。 | D11: =int_ai_sample_v2!F11 -> neutral | E11: =人工標注!F11 -> neutral | F11: =IF(D11=E11,"是","否") -> 是 | G11: =COUNTIF($F$2:$F$101,"是")/COUNTA($A$2:$A$101) -> 0.87 | H11: =IF(int_ai_sample_v2!G11=人工標注!G11,"是","否") -> 是 | I11: =IF(int_ai_sample_v2!H11=人工標注!H11,"是","否") -> 是 | J11: =IF(int_ai_sample_v2!I11=人工標注!I11,"是","否") -> 是 | K11: =IF(int_ai_sample_v2!J11=人工標注!J11,"是","否") -> 是 | L11: =IF(int_ai_sample_v2!K11=人工標注!K11,"是","否") -> 是 | M11: =IF(int_ai_sample_v2!L11=人工標注!L11,"是","否") -> 是 | N11: =IF(int_ai_sample_v2!M11=人工標注!M11,"是","否") -> 是 | O11: =IF(int_ai_sample_v2!N11=人工標注!N11,"是","否") -> 是 | R11: T06 | S11: =COUNTIFS(int_ai_sample_v2!$L$2:$L$101,1,人工標注!$L$2:$L$101,1) -> 9 | T11: =COUNTIFS(int_ai_sample_v2!$L$2:$L$101,1,人工標注!$L$2:$L$101,0) -> 9 | U11: =COUNTIFS(int_ai_sample_v2!$L$2:$L$101,0,人工標注!$L$2:$L$101,1) -> 0 | V11: =COUNTIFS(int_ai_sample_v2!$L$2:$L$101,0,人工標注!$L$2:$L$101,0) -> 82 | W11: =IF(S11+T11=0,0,S11/(S11+T11)) -> 0.5 | X11: =IF(S11+U11=0,0,S11/(S11+U11)) -> 1 | Y11: =IF(W11+X11=0,0,2*W11*X11/(W11+X11)) -> 0.66666667 | Z11: =S11+U11 -> 9
A12: 190f5817bf369b18149d2fd6fea8ed5c | B12: 1 | C12: 我還沒收到！ | D12: =int_ai_sample_v2!F12 -> negative | E12: =人工標注!F12 -> negative | F12: =IF(D12=E12,"是","否") -> 是 | G12: =COUNTIF($F$2:$F$101,"是")/COUNTA($A$2:$A$101) -> 0.87 | H12: =IF(int_ai_sample_v2!G12=人工標注!G12,"是","否") -> 是 | I12: =IF(int_ai_sample_v2!H12=人工標注!H12,"是","否") -> 是 | J12: =IF(int_ai_sample_v2!I12=人工標注!I12,"是","否") -> 是 | K12: =IF(int_ai_sample_v2!J12=人工標注!J12,"是","否") -> 是 | L12: =IF(int_ai_sample_v2!K12=人工標注!K12,"是","否") -> 是 | M12: =IF(int_ai_sample_v2!L12=人工標注!L12,"是","否") -> 是 | N12: =IF(int_ai_sample_v2!M12=人工標注!M12,"是","否") -> 是 | O12: =IF(int_ai_sample_v2!N12=人工標注!N12,"是","否") -> 是 | R12: T07 | S12: =COUNTIFS(int_ai_sample_v2!$M$2:$M$101,1,人工標注!$M$2:$M$101,1) -> 4 | T12: =COUNTIFS(int_ai_sample_v2!$M$2:$M$101,1,人工標注!$M$2:$M$101,0) -> 3 | U12: =COUNTIFS(int_ai_sample_v2!$M$2:$M$101,0,人工標注!$M$2:$M$101,1) -> 1 | V12: =COUNTIFS(int_ai_sample_v2!$M$2:$M$101,0,人工標注!$M$2:$M$101,0) -> 92 | W12: =IF(S12+T12=0,0,S12/(S12+T12)) -> 0.57142857 | X12: =IF(S12+U12=0,0,S12/(S12+U12)) -> 0.8 | Y12: =IF(W12+X12=0,0,2*W12*X12/(W12+X12)) -> 0.66666667 | Z12: =S12+U12 -> 5
A13: 1937557c43952cfaafa9474b8a0a0f2d | B13: 5 | C13: 我超級推薦！也祝賀你們對消費者的尊重！ | D13: =int_ai_sample_v2!F13 -> positive | E13: =人工標注!F13 -> positive | F13: =IF(D13=E13,"是","否") -> 是 | G13: =COUNTIF($F$2:$F$101,"是")/COUNTA($A$2:$A$101) -> 0.87 | H13: =IF(int_ai_sample_v2!G13=人工標注!G13,"是","否") -> 是 | I13: =IF(int_ai_sample_v2!H13=人工標注!H13,"是","否") -> 是 | J13: =IF(int_ai_sample_v2!I13=人工標注!I13,"是","否") -> 是 | K13: =IF(int_ai_sample_v2!J13=人工標注!J13,"是","否") -> 是 | L13: =IF(int_ai_sample_v2!K13=人工標注!K13,"是","否") -> 是 | M13: =IF(int_ai_sample_v2!L13=人工標注!L13,"是","否") -> 否 | N13: =IF(int_ai_sample_v2!M13=人工標注!M13,"是","否") -> 是 | O13: =IF(int_ai_sample_v2!N13=人工標注!N13,"是","否") -> 是 | R13: T08 | S13: =COUNTIFS(int_ai_sample_v2!$N$2:$N$101,1,人工標注!$N$2:$N$101,1) -> 2 | T13: =COUNTIFS(int_ai_sample_v2!$N$2:$N$101,1,人工標注!$N$2:$N$101,0) -> 0 | U13: =COUNTIFS(int_ai_sample_v2!$N$2:$N$101,0,人工標注!$N$2:$N$101,1) -> 2 | V13: =COUNTIFS(int_ai_sample_v2!$N$2:$N$101,0,人工標注!$N$2:$N$101,0) -> 96 | W13: =IF(S13+T13=0,0,S13/(S13+T13)) -> 1 | X13: =IF(S13+U13=0,0,S13/(S13+U13)) -> 0.5 | Y13: =IF(W13+X13=0,0,2*W13*X13/(W13+X13)) -> 0.66666667 | Z13: =S13+U13 -> 4
A14: 21791c8e73d5a4531d9b835a5ea4c1e1 | B14: 3 | C14: 我付了運費請他們送到家，但很不幸我還是得去郵局領貨。我覺得被騙了，因為他們收了運費卻沒有送到。 | D14: =int_ai_sample_v2!F14 -> negative | E14: =人工標注!F14 -> negative | F14: =IF(D14=E14,"是","否") -> 是 | G14: =COUNTIF($F$2:$F$101,"是")/COUNTA($A$2:$A$101) -> 0.87 | H14: =IF(int_ai_sample_v2!G14=人工標注!G14,"是","否") -> 是 | I14: =IF(int_ai_sample_v2!H14=人工標注!H14,"是","否") -> 是 | J14: =IF(int_ai_sample_v2!I14=人工標注!I14,"是","否") -> 是 | K14: =IF(int_ai_sample_v2!J14=人工標注!J14,"是","否") -> 是 | L14: =IF(int_ai_sample_v2!K14=人工標注!K14,"是","否") -> 是 | M14: =IF(int_ai_sample_v2!L14=人工標注!L14,"是","否") -> 是 | N14: =IF(int_ai_sample_v2!M14=人工標注!M14,"是","否") -> 是 | O14: =IF(int_ai_sample_v2!N14=人工標注!N14,"是","否") -> 是
A15: 27653a377d5279da3480d0b79db976e5 | B15: 4 | C15: 推薦。我喜歡配送的效率。 | D15: =int_ai_sample_v2!F15 -> positive | E15: =人工標注!F15 -> positive | F15: =IF(D15=E15,"是","否") -> 是 | G15: =COUNTIF($F$2:$F$101,"是")/COUNTA($A$2:$A$101) -> 0.87 | H15: =IF(int_ai_sample_v2!G15=人工標注!G15,"是","否") -> 是 | I15: =IF(int_ai_sample_v2!H15=人工標注!H15,"是","否") -> 是 | J15: =IF(int_ai_sample_v2!I15=人工標注!I15,"是","否") -> 是 | K15: =IF(int_ai_sample_v2!J15=人工標注!J15,"是","否") -> 是 | L15: =IF(int_ai_sample_v2!K15=人工標注!K15,"是","否") -> 是 | M15: =IF(int_ai_sample_v2!L15=人工標注!L15,"是","否") -> 是 | N15: =IF(int_ai_sample_v2!M15=人工標注!M15,"是","否") -> 是 | O15: =IF(int_ai_sample_v2!N15=人工標注!N15,"是","否") -> 是 | R15: Macro avg | W15: =AVERAGE(W6:W13) -> 0.73707707 | X15: =AVERAGE(X6:X13) -> 0.77544757 | Y15: =AVERAGE(Y6:Y13) -> 0.7099023 | Z15: =SUM(Z6:Z13) -> 107
A16: 2893f7f537bc5056b7bbb42a742d56ad | B16: 1 | C16: 沒有聯絡我來解決退回購買款的問題。 | D16: =int_ai_sample_v2!F16 -> negative | E16: =人工標注!F16 -> negative | F16: =IF(D16=E16,"是","否") -> 是 | G16: =COUNTIF($F$2:$F$101,"是")/COUNTA($A$2:$A$101) -> 0.87 | H16: =IF(int_ai_sample_v2!G16=人工標注!G16,"是","否") -> 是 | I16: =IF(int_ai_sample_v2!H16=人工標注!H16,"是","否") -> 是 | J16: =IF(int_ai_sample_v2!I16=人工標注!I16,"是","否") -> 是 | K16: =IF(int_ai_sample_v2!J16=人工標注!J16,"是","否") -> 是 | L16: =IF(int_ai_sample_v2!K16=人工標注!K16,"是","否") -> 是 | M16: =IF(int_ai_sample_v2!L16=人工標注!L16,"是","否") -> 是 | N16: =IF(int_ai_sample_v2!M16=人工標注!M16,"是","否") -> 是 | O16: =IF(int_ai_sample_v2!N16=人工標注!N16,"是","否") -> 是 | R16: Micro avg | S16: =SUM(S6:S13) -> 91 | T16: =SUM(T6:T13) -> 31 | U16: =SUM(U6:U13) -> 16 | V16: =SUM(V6:V13) -> 662 | W16: =IF(S16+T16=0,0,S16/(S16+T16)) -> 0.74590164 | X16: =IF(S16+U16=0,0,S16/(S16+U16)) -> 0.85046729 | Y16: =IF(W16+X16=0,0,2*W16*X16/(W16+X16)) -> 0.79475983 | Z16: =SUM(Z6:Z13) -> 107
A17: 297cb67099f7e259f215ed6a518acb76 | B17: 3 | C17: 我們只收到了嬰兒舒適座椅（bêbe conforto）。推車沒有一起來。 | D17: =int_ai_sample_v2!F17 -> negative | E17: =人工標注!F17 -> negative | F17: =IF(D17=E17,"是","否") -> 是 | G17: =COUNTIF($F$2:$F$101,"是")/COUNTA($A$2:$A$101) -> 0.87 | H17: =IF(int_ai_sample_v2!G17=人工標注!G17,"是","否") -> 是 | I17: =IF(int_ai_sample_v2!H17=人工標注!H17,"是","否") -> 是 | J17: =IF(int_ai_sample_v2!I17=人工標注!I17,"是","否") -> 是 | K17: =IF(int_ai_sample_v2!J17=人工標注!J17,"是","否") -> 是 | L17: =IF(int_ai_sample_v2!K17=人工標注!K17,"是","否") -> 是 | M17: =IF(int_ai_sample_v2!L17=人工標注!L17,"是","否") -> 是 | N17: =IF(int_ai_sample_v2!M17=人工標注!M17,"是","否") -> 是 | O17: =IF(int_ai_sample_v2!N17=人工標注!N17,"是","否") -> 是
A18: 2b1548b7746b6470035ec1202aa5e914 | B18: 1 | C18: 我不推薦。商品已經壞掉，而且超過一週我一直在嘗試解決，但沒有人回應，這太離譜了，因為我付的是全額，不是付一半。 | D18: =int_ai_sample_v2!F18 -> negative | E18: =人工標注!F18 -> negative | F18: =IF(D18=E18,"是","否") -> 是 | G18: =COUNTIF($F$2:$F$101,"是")/COUNTA($A$2:$A$101) -> 0.87 | H18: =IF(int_ai_sample_v2!G18=人工標注!G18,"是","否") -> 是 | I18: =IF(int_ai_sample_v2!H18=人工標注!H18,"是","否") -> 是 | J18: =IF(int_ai_sample_v2!I18=人工標注!I18,"是","否") -> 是 | K18: =IF(int_ai_sample_v2!J18=人工標注!J18,"是","否") -> 是 | L18: =IF(int_ai_sample_v2!K18=人工標注!K18,"是","否") -> 是 | M18: =IF(int_ai_sample_v2!L18=人工標注!L18,"是","否") -> 是 | N18: =IF(int_ai_sample_v2!M18=人工標注!M18,"是","否") -> 否 | O18: =IF(int_ai_sample_v2!N18=人工標注!N18,"是","否") -> 是
A19: 2d252afef013ea5392e79df6173acc9b | B19: 2 | C19: 手錶沒有盒子嗎？雖然包裝得很好，但沒有盒子？ | D19: =int_ai_sample_v2!F19 -> neutral | E19: =人工標注!F19 -> mixed | F19: =IF(D19=E19,"是","否") -> 否 | G19: =COUNTIF($F$2:$F$101,"是")/COUNTA($A$2:$A$101) -> 0.87 | H19: =IF(int_ai_sample_v2!G19=人工標注!G19,"是","否") -> 是 | I19: =IF(int_ai_sample_v2!H19=人工標注!H19,"是","否") -> 否 | J19: =IF(int_ai_sample_v2!I19=人工標注!I19,"是","否") -> 是 | K19: =IF(int_ai_sample_v2!J19=人工標注!J19,"是","否") -> 是 | L19: =IF(int_ai_sample_v2!K19=人工標注!K19,"是","否") -> 是 | M19: =IF(int_ai_sample_v2!L19=人工標注!L19,"是","否") -> 是 | N19: =IF(int_ai_sample_v2!M19=人工標注!M19,"是","否") -> 是 | O19: =IF(int_ai_sample_v2!N19=人工標注!N19,"是","否") -> 是
A20: 3639e59f95a0241360cc0c52933c5493 | B20: 5 | C20: 這是一家很棒的店，能滿足使用者需求，商品也在預定時間之前送達。 | D20: =int_ai_sample_v2!F20 -> positive | E20: =人工標注!F20 -> positive | F20: =IF(D20=E20,"是","否") -> 是 | G20: =COUNTIF($F$2:$F$101,"是")/COUNTA($A$2:$A$101) -> 0.87 | H20: =IF(int_ai_sample_v2!G20=人工標注!G20,"是","否") -> 是 | I20: =IF(int_ai_sample_v2!H20=人工標注!H20,"是","否") -> 是 | J20: =IF(int_ai_sample_v2!I20=人工標注!I20,"是","否") -> 是 | K20: =IF(int_ai_sample_v2!J20=人工標注!J20,"是","否") -> 是 | L20: =IF(int_ai_sample_v2!K20=人工標注!K20,"是","否") -> 是 | M20: =IF(int_ai_sample_v2!L20=人工標注!L20,"是","否") -> 是 | N20: =IF(int_ai_sample_v2!M20=人工標注!M20,"是","否") -> 是 | O20: =IF(int_ai_sample_v2!N20=人工標注!N20,"是","否") -> 是
A21: 37749bb373f353f47ccc414e6250249e | B21: 5 | C21: 比預定時間還早送達。 | D21: =int_ai_sample_v2!F21 -> positive | E21: =人工標注!F21 -> positive | F21: =IF(D21=E21,"是","否") -> 是 | G21: =COUNTIF($F$2:$F$101,"是")/COUNTA($A$2:$A$101) -> 0.87 | H21: =IF(int_ai_sample_v2!G21=人工標注!G21,"是","否") -> 是 | I21: =IF(int_ai_sample_v2!H21=人工標注!H21,"是","否") -> 是 | J21: =IF(int_ai_sample_v2!I21=人工標注!I21,"是","否") -> 是 | K21: =IF(int_ai_sample_v2!J21=人工標注!J21,"是","否") -> 是 | L21: =IF(int_ai_sample_v2!K21=人工標注!K21,"是","否") -> 是 | M21: =IF(int_ai_sample_v2!L21=人工標注!L21,"是","否") -> 是 | N21: =IF(int_ai_sample_v2!M21=人工標注!M21,"是","否") -> 是 | O21: =IF(int_ai_sample_v2!N21=人工標注!N21,"是","否") -> 是
A22: 3a51ddc1205b69754d418863af82bdfc | B22: 1 | C22: 商品的調整按鈕有瑕疵。 | D22: =int_ai_sample_v2!F22 -> negative | E22: =人工標注!F22 -> negative | F22: =IF(D22=E22,"是","否") -> 是 | G22: =COUNTIF($F$2:$F$101,"是")/COUNTA($A$2:$A$101) -> 0.87 | H22: =IF(int_ai_sample_v2!G22=人工標注!G22,"是","否") -> 是 | I22: =IF(int_ai_sample_v2!H22=人工標注!H22,"是","否") -> 是 | J22: =IF(int_ai_sample_v2!I22=人工標注!I22,"是","否") -> 是 | K22: =IF(int_ai_sample_v2!J22=人工標注!J22,"是","否") -> 是 | L22: =IF(int_ai_sample_v2!K22=人工標注!K22,"是","否") -> 是 | M22: =IF(int_ai_sample_v2!L22=人工標注!L22,"是","否") -> 是 | N22: =IF(int_ai_sample_v2!M22=人工標注!M22,"是","否") -> 是 | O22: =IF(int_ai_sample_v2!N22=人工標注!N22,"是","否") -> 是
A23: 3aae92074840202a7fac32bb5b163576 | B23: 5 | C23: 我推薦！！ | D23: =int_ai_sample_v2!F23 -> positive | E23: =人工標注!F23 -> positive | F23: =IF(D23=E23,"是","否") -> 是 | G23: =COUNTIF($F$2:$F$101,"是")/COUNTA($A$2:$A$101) -> 0.87 | H23: =IF(int_ai_sample_v2!G23=人工標注!G23,"是","否") -> 是 | I23: =IF(int_ai_sample_v2!H23=人工標注!H23,"是","否") -> 是 | J23: =IF(int_ai_sample_v2!I23=人工標注!I23,"是","否") -> 是 | K23: =IF(int_ai_sample_v2!J23=人工標注!J23,"是","否") -> 是 | L23: =IF(int_ai_sample_v2!K23=人工標注!K23,"是","否") -> 是 | M23: =IF(int_ai_sample_v2!L23=人工標注!L23,"是","否") -> 是 | N23: =IF(int_ai_sample_v2!M23=人工標注!M23,"是","否") -> 是 | O23: =IF(int_ai_sample_v2!N23=人工標注!N23,"是","否") -> 是
A24: 3b850443ee703ff8381534dc0349847d | B24: 1 | C24: 客服很糟。你們賣的是你們沒有的商品。我再也不會在這個網站買了。沒有任何星星。只有一顆是因為我被迫要勾選送出回覆。0分。 | D24: =int_ai_sample_v2!F24 -> negative | E24: =人工標注!F24 -> negative | F24: =IF(D24=E24,"是","否") -> 是 | G24: =COUNTIF($F$2:$F$101,"是")/COUNTA($A$2:$A$101) -> 0.87 | H24: =IF(int_ai_sample_v2!G24=人工標注!G24,"是","否") -> 是 | I24: =IF(int_ai_sample_v2!H24=人工標注!H24,"是","否") -> 是 | J24: =IF(int_ai_sample_v2!I24=人工標注!I24,"是","否") -> 是 | K24: =IF(int_ai_sample_v2!J24=人工標注!J24,"是","否") -> 否 | L24: =IF(int_ai_sample_v2!K24=人工標注!K24,"是","否") -> 是 | M24: =IF(int_ai_sample_v2!L24=人工標注!L24,"是","否") -> 是 | N24: =IF(int_ai_sample_v2!M24=人工標注!M24,"是","否") -> 是 | O24: =IF(int_ai_sample_v2!N24=人工標注!N24,"是","否") -> 是
A25: 4056b7f9e9c1a158d122a0460f59fedb | B25: 4 | C25: 做錯的地方不是 stark 的問題：郵局說三次嘗試都沒人，雖然我媽媽和其他人一直都在家，還有用郵局線上 app 一直看。 | D25: =int_ai_sample_v2!F25 -> negative | E25: =人工標注!F25 -> negative | F25: =IF(D25=E25,"是","否") -> 是 | G25: =COUNTIF($F$2:$F$101,"是")/COUNTA($A$2:$A$101) -> 0.87 | H25: =IF(int_ai_sample_v2!G25=人工標注!G25,"是","否") -> 是 | I25: =IF(int_ai_sample_v2!H25=人工標注!H25,"是","否") -> 是 | J25: =IF(int_ai_sample_v2!I25=人工標注!I25,"是","否") -> 是 | K25: =IF(int_ai_sample_v2!J25=人工標注!J25,"是","否") -> 是 | L25: =IF(int_ai_sample_v2!K25=人工標注!K25,"是","否") -> 是 | M25: =IF(int_ai_sample_v2!L25=人工標注!L25,"是","否") -> 是 | N25: =IF(int_ai_sample_v2!M25=人工標注!M25,"是","否") -> 是 | O25: =IF(int_ai_sample_v2!N25=人工標注!N25,"是","否") -> 是
A26: 45d042517e196746c0cb856f48414154 | B26: 4 | C26: 服務很好，且預定的送達時間也有準時達成。 | D26: =int_ai_sample_v2!F26 -> positive | E26: =人工標注!F26 -> positive | F26: =IF(D26=E26,"是","否") -> 是 | G26: =COUNTIF($F$2:$F$101,"是")/COUNTA($A$2:$A$101) -> 0.87 | H26: =IF(int_ai_sample_v2!G26=人工標注!G26,"是","否") -> 是 | I26: =IF(int_ai_sample_v2!H26=人工標注!H26,"是","否") -> 是 | J26: =IF(int_ai_sample_v2!I26=人工標注!I26,"是","否") -> 是 | K26: =IF(int_ai_sample_v2!J26=人工標注!J26,"是","否") -> 是 | L26: =IF(int_ai_sample_v2!K26=人工標注!K26,"是","否") -> 是 | M26: =IF(int_ai_sample_v2!L26=人工標注!L26,"是","否") -> 否 | N26: =IF(int_ai_sample_v2!M26=人工標注!M26,"是","否") -> 是 | O26: =IF(int_ai_sample_v2!N26=人工標注!N26,"是","否") -> 是
A27: 463a721864bf46834a9a31c8cd8180d8 | B27: 3 | C27: 我很討厭用郵局寄送，因為最後我得去郵局領貨，會浪費時間；而且郵局沒有送到家裡的物流，附近還都是風險地區。 | D27: =int_ai_sample_v2!F27 -> negative | E27: =人工標注!F27 -> negative | F27: =IF(D27=E27,"是","否") -> 是 | G27: =COUNTIF($F$2:$F$101,"是")/COUNTA($A$2:$A$101) -> 0.87 | H27: =IF(int_ai_sample_v2!G27=人工標注!G27,"是","否") -> 是 | I27: =IF(int_ai_sample_v2!H27=人工標注!H27,"是","否") -> 是 | J27: =IF(int_ai_sample_v2!I27=人工標注!I27,"是","否") -> 是 | K27: =IF(int_ai_sample_v2!J27=人工標注!J27,"是","否") -> 是 | L27: =IF(int_ai_sample_v2!K27=人工標注!K27,"是","否") -> 是 | M27: =IF(int_ai_sample_v2!L27=人工標注!L27,"是","否") -> 是 | N27: =IF(int_ai_sample_v2!M27=人工標注!M27,"是","否") -> 是 | O27: =IF(int_ai_sample_v2!N27=人工標注!N27,"是","否") -> 是
A28: 4a746391af112fb32935992ad3d0e913 | B28: 2 | C28: 關於修剪機（修毛機）我收到很快，但同一天我也下了修指甲刀的訂單。這兩樣在同一張帳單、用同一張信用卡都有被扣款；但截至目前還沒收到。 | D28: =int_ai_sample_v2!F28 -> negative | E28: =人工標注!F28 -> negative | F28: =IF(D28=E28,"是","否") -> 是 | G28: =COUNTIF($F$2:$F$101,"是")/COUNTA($A$2:$A$101) -> 0.87 | H28: =IF(int_ai_sample_v2!G28=人工標注!G28,"是","否") -> 是 | I28: =IF(int_ai_sample_v2!H28=人工標注!H28,"是","否") -> 否 | J28: =IF(int_ai_sample_v2!I28=人工標注!I28,"是","否") -> 是 | K28: =IF(int_ai_sample_v2!J28=人工標注!J28,"是","否") -> 是 | L28: =IF(int_ai_sample_v2!K28=人工標注!K28,"是","否") -> 是 | M28: =IF(int_ai_sample_v2!L28=人工標注!L28,"是","否") -> 是 | N28: =IF(int_ai_sample_v2!M28=人工標注!M28,"是","否") -> 否 | O28: =IF(int_ai_sample_v2!N28=人工標注!N28,"是","否") -> 是
... A101: fcaf726c0b61b07ef40c8bc2a3e9eeb2 | B101: 4 | C101: 其他次都一切OK，這次不知道發生了什麼。 | D101: =int_ai_sample_v2!F101 -> neutral | E101: =人工標注!F101 -> negative | F101: =IF(D101=E101,"是","否") -> 否 | G101: =COUNTIF($F$2:$F$101,"是")/COUNTA($A$2:$A$101) -> 0.87 | H101: =IF(int_ai_sample_v2!G101=人工標注!G101,"是","否") -> 是 | I101: =IF(int_ai_sample_v2!H101=人工標注!H101,"是","否") -> 是 | J101: =IF(int_ai_sample_v2!I101=人工標注!I101,"是","否") -> 是 | K101: =IF(int_ai_sample_v2!J101=人工標注!J101,"是","否") -> 是 | L101: =IF(int_ai_sample_v2!K101=人工標注!K101,"是","否") -> 是 | M101: =IF(int_ai_sample_v2!L101=人工標注!L101,"是","否") -> 是 | N101: =IF(int_ai_sample_v2!M101=人工標注!M101,"是","否") -> 是 | O101: =IF(int_ai_sample_v2!N101=人工標注!N101,"是","否") -> 是
